Workbook

Sheet Summary
A1: Sitpur Banana + Multi-fruit Packhouse, Pre-cooling & Cold Storage – Unit Economics
A2: Farm: Sitpur Estate, Dabhoi, 150 acres (owner plan). Packhouse fruits: banana (own) + papaya + Kesar mango (procured). Prices & costs researched Sep-2026. All live formulas.
A4: Running days & capacity (change on Inputs)
B5: Packhouse | C5: Pre-cooling | D5: Cold storage
A6: Running days per year | B6: =Inputs!$B$8 -> 300 | C6: =Inputs!$B$9 -> 300 | D6: =Inputs!$B$10 -> 330 | F6: Estimates – edit on Inputs
A7: Utilisation | B7: ='Operations & Capacity'!$B$13 -> 0.75789474 | C7: ='Operations & Capacity'!$E$29 -> 0.58378947 | D7: ='Operations & Capacity'!$E$33 -> 0.86108421 | F7: Banana line / pre-cooling / cold-store peak
A8: Opex per year (₹) | B8: ='Packhouse Opex'!$B$37 -> 14210963 | C8: ='Packhouse Opex'!$B$38 -> 1806657.5 | D8: ='Packhouse Opex'!$B$39 -> 1526140
A9: Capex (₹) | B9: ='Packhouse Capex'!$E$10 -> 12250000 | C9: ='Packhouse Capex'!$E$13 -> 9000000 | D9: ='Packhouse Capex'!$E$16 -> 2200000
A10: Full cost per kg through (incl. depreciation & interest) | B10: ='Packhouse Opex'!$G$37 -> 2.090277 | C10: ='Packhouse Opex'!$G$38 -> 0.46815039 | D10: ='Packhouse Opex'!$G$39 -> 0.28644712
A12: Volumes (t/yr)
B13: Banana | C13: Papaya | D13: Mango | E13: Total
A14: Processed through packhouse | B14: ='Operations & Capacity'!$B$11 -> 5684.2105 | C14: ='Operations & Capacity'!$C$11 -> 1440 | D14: ='Operations & Capacity'!$D$11 -> 360 | E14: ='Operations & Capacity'!$E$11 -> 7484.2105
A15: Sellable packed | B15: ='Operations & Capacity'!$B$19 -> 4635.9284 | C15: ='Operations & Capacity'!$C$19 -> 1248.192 | D15: ='Operations & Capacity'!$D$19 -> 326.232 | E15: ='Operations & Capacity'!$E$19 -> 6210.3524
A16: Banana harvest / surplus sold at farm gate | B16: ='Farm Plan'!$D$40 -> 5684.2105 | C16: ='Operations & Capacity'!$B$12 -> 0 | F16: Col B harvest, col C unprocessed surplus
A17: Export containers per year | B17: ='Operations & Capacity'!$B$23 -> 57.891214
A19: Unit economics (₹ per kg sellable)
B20: Banana export | C20: Banana domestic | D20: Papaya | E20: Kesar mango
A21: Selling price | B21: ='Unit Economics'!$B$5 -> 51.692308 | C21: ='Unit Economics'!$C$5 -> 28 | D21: ='Unit Economics'!$D$5 -> 26 | E21: ='Unit Economics'!$E$5 -> 120
A22: Fruit cost (farm / procurement) | B22: ='Unit Economics'!$B$7 -> 8.9144159 | C22: ='Unit Economics'!$C$7 -> 8.9144159 | D22: ='Unit Economics'!$D$7 -> 14.997693 | E22: ='Unit Economics'!$E$7 -> 80.556169
A23: Pre-cooling | B23: ='Unit Economics'!$B$11 -> 0.29091062 | C23: ='Unit Economics'!$C$11 -> 0.29091062 | D23: ='Unit Economics'!$D$11 -> 0.29091062 | E23: ='Unit Economics'!$E$11 -> 0.29091062
A24: Cold storage | B24: ='Unit Economics'!$B$12 -> 0.24574129 | C24: ='Unit Economics'!$C$12 -> 0.24574129 | D24: ='Unit Economics'!$D$12 -> 0.24574129 | E24: ='Unit Economics'!$E$12 -> 0.24574129
A25: Packaging | B25: ='Unit Economics'!$B$13 -> 7.5384615 | C25: ='Unit Economics'!$C$13 -> 5.1538462 | D25: ='Unit Economics'!$D$13 -> 2 | E25: ='Unit Economics'!$E$13 -> 11.666667
A26: Freight (incl. ocean + surcharge for export) | B26: ='Unit Economics'!$B$15+'Unit Economics'!$B$17+'Unit Economics'!$B$18+'Unit Economics'!$B$16 -> 33.866134 | C26: ='Unit Economics'!$C$15+'Unit Economics'!$C$17+'Unit Economics'!$C$18+'Unit Economics'!$C$16 -> 4.7555556 | D26: ='Unit Economics'!$D$15+'Unit Economics'!$D$17+'Unit Economics'!$D$18+'Unit Economics'!$D$16 -> 2.8333333 | E26: ='Unit Economics'!$E$15+'Unit Economics'!$E$17+'Unit Economics'!$E$18+'Unit Economics'!$E$16 -> 4.7555556
A27: Total cost | B27: ='Unit Economics'!$B$25 -> 58.24593 | C27: ='Unit Economics'!$C$25 -> 25.160363 | D27: ='Unit Economics'!$D$25 -> 25.032471 | E27: ='Unit Economics'!$E$25 -> 106.21668
A28: Net margin | B28: ='Unit Economics'!$B$26 -> -6.5536227 | C28: ='Unit Economics'!$C$26 -> 2.8396367 | D28: ='Unit Economics'!$D$26 -> 0.96752918 | E28: ='Unit Economics'!$E$26 -> 13.783315
A29: Net margin % | B29: ='Unit Economics'!$B$27 -> -0.12678139 | C29: ='Unit Economics'!$C$27 -> 0.1014156 | D29: ='Unit Economics'!$D$27 -> 0.037212661 | E29: ='Unit Economics'!$E$27 -> 0.11486096
A30: Net margin per year (₹) | B30: ='Unit Economics'!$B$30 -> -7595531.5 | C30: ='Unit Economics'!$C$30 -> 9873264.3 | D30: ='Unit Economics'!$D$30 -> 1207662.2 | E30: ='Unit Economics'!$E$30 -> 4496558.4
A32: Annual P&L (₹ lakh)
B33: Sep-2026 conditions | C33: Normalised (no surcharge)
A34: Total revenue | B34: ='Annual P&L'!$B$13/100000 -> 2491.6069 | C34: ='Annual P&L'!$D$13/100000 -> 2491.6069
A35: Total operating cost | B35: ='Annual P&L'!$B$29/100000 -> 2273.165 | C35: ='Annual P&L'!$D$29/100000 -> 2050.8627
A36: EBITDA | B36: ='Annual P&L'!$B$30/100000 -> 218.44193 | C36: ='Annual P&L'!$D$30/100000 -> 440.74419
A37: Profit before tax | B37: ='Annual P&L'!$B$34/100000 -> 153.46334 | C37: ='Annual P&L'!$D$34/100000 -> 375.7656
A38: Packhouse business EBITDA (farm paid farm-gate price) | B38: ='Annual P&L'!$B$41/100000 -> -97.94702 | C38: ='Annual P&L'!$D$41/100000 -> 124.35524
A39: Net packhouse capex after subsidy | B39: ='Annual P&L'!$B$40/100000 -> 312.025 | C39: ='Annual P&L'!$D$40/100000 -> 312.025
A40: Payback on value added (years) | B40: ='Annual P&L'!$B$42 -> n/a | C40: ='Annual P&L'!$D$42 -> 2.5091423
A42: Rotation crop (per acre, before rent)
B43: Papaya | C43: Watermelon | D43: Green manure | E43: Banana (benchmark)
A44: Margin per acre per crop (₹) | B44: ='Crop Rotation'!$B$14 -> 360000 | C44: ='Crop Rotation'!$C$14 -> -20844 | D44: ='Crop Rotation'!$D$14 -> -5280
A45: Margin per acre per month (₹) | B45: ='Crop Rotation'!$B$15 -> 18000 | C45: ='Crop Rotation'!$C$15 -> -6948 | D45: ='Crop Rotation'!$D$15 -> -2640 | E45: ='Crop Rotation'!$B$16 -> 31578.947
A47: Key findings (update automatically)
A48: ="1. Running days: packhouse "&Inputs!$B$8&", pre-cooling "&Inputs!$B$9&", cold storage "&Inputs!$B$10&" days/yr. The banana line runs at "&TEXT('Operations & Capacity'!$B$13,"0%")&" of capacity; pre-cooling peaks at "&TEXT('Operations & Capacity'!$E$29,"0%")&". Cut the days and surplus banana ("&TEXT('Operations & Capacity'!$B$12,"0")&" t now) is sold at the farm gate instead." -> 1. Running days: packhouse 300, pre-cooling 300, cold storage 330 days/yr. The banana line runs at 76% of capacity; pre-cooling peaks at 58%. Cut the days and surplus banana (0 t now) is sold at the farm gate instead.
A49: ="2. Pre-cooling costs ₹"&TEXT('Packhouse Opex'!$G$38,"0.00")&"/kg and cold storage ₹"&TEXT('Packhouse Opex'!$G$39,"0.00")&"/kg of fruit (power, staff, repairs, depreciation, interest). Capex for the two together: ₹"&TEXT(('Packhouse Capex'!$E$13+'Packhouse Capex'!$E$16)/100000,"0")&" lakh." -> 2. Pre-cooling costs ₹0.47/kg and cold storage ₹0.29/kg of fruit (power, staff, repairs, depreciation, interest). Capex for the two together: ₹112 lakh.
A50: ="3. Kesar mango earns ₹"&TEXT('Unit Economics'!$E$26,"0")&"/kg net (₹"&TEXT('Unit Economics'!$E$30/100000,"0")&" lakh/yr in "&Inputs!$B$86&" days). Papaya earns ₹"&TEXT('Unit Economics'!$D$26,"0.0")&"/kg (₹"&TEXT('Unit Economics'!$D$30/100000,"0")&" lakh/yr). Banana domestic earns ₹"&TEXT('Unit Economics'!$C$26,"0.0")&"/kg; banana export ₹"&TEXT('Unit Economics'!$B$26,"0.0")&"/kg with the Gulf surcharge." -> 3. Kesar mango earns ₹14/kg net (₹45 lakh/yr in 60 days). Papaya earns ₹1.0/kg (₹12 lakh/yr). Banana domestic earns ₹2.8/kg; banana export ₹-6.6/kg with the Gulf surcharge.
A51: ="4. Whole business EBITDA is ₹"&TEXT('Annual P&L'!$B$30/100000,"0")&" lakh now vs ₹"&TEXT('Annual P&L'!$D$30/100000,"0")&" lakh in a normalised shipping year. If the farm is paid the ₹"&TEXT('Farm Plan'!$D$47,"0.0")&"/kg farm-gate price, the packhouse business makes ₹"&TEXT('Annual P&L'!$B$41/100000,"0")&" lakh now and ₹"&TEXT('Annual P&L'!$D$41/100000,"0")&" lakh normalised." -> 4. Whole business EBITDA is ₹218 lakh now vs ₹441 lakh in a normalised shipping year. If the farm is paid the ₹13.5/kg farm-gate price, the packhouse business makes ₹-98 lakh now and ₹124 lakh normalised.
A52: ="5. Watch-out: domestic banana must sell above ₹"&TEXT('Unit Economics'!$C$33,"0.0")&"/kg delivered (you assume ₹"&TEXT(Inputs!$B$108,"0")&") before packing beats selling at the farm gate. The 18% pack-out loss (stalk, culls, shrink), packaging and freight eat most of the premium. Lock in a premium contract before building." -> 5. Watch-out: domestic banana must sell above ₹31.7/kg delivered (you assume ₹28) before packing beats selling at the farm gate. The 18% pack-out loss (stalk, culls, shrink), packaging and freight eat most of the premium. Lock in a premium contract before building.
A53: ="6. Rotation: papaya makes ₹"&TEXT('Crop Rotation'!$B$15,"#,##0")&"/acre/month vs banana ₹"&TEXT('Crop Rotation'!$B$16,"#,##0")&". It is the best backup crop and feeds your own papaya line. Watermelon makes ₹"&TEXT('Crop Rotation'!$C$15,"#,##0")&"/acre/month – use it only as a filler. Sow green manure before each replant." -> 6. Rotation: papaya makes ₹18,000/acre/month vs banana ₹31,579. It is the best backup crop and feeds your own papaya line. Watermelon makes ₹-6,948/acre/month – use it only as a filler. Sow green manure before each replant.
A54: 7. All harvest and loading wages are capped at ₹1,000/day (Inputs → labour cap). The farm plan's ₹400/day for permanent workers is below Gujarat's minimum wage of ₹501–512/day – check this.
A56: Blue = input · Black = formula · Green = link to another tab · Yellow = no reliable figure found (left blank). Key levers are highlighted on Inputs: running days, labour cap, yield shortfall, rotation acres, war-risk switch.

Sheet Inputs
A1: Inputs & Assumptions – change blue cells; every tab recalculates
A2: Blue = input · Yellow = no reliable figure found, left blank · Confidence: User (your plan/DPR/notes) / Researched / Derived / Estimate. [S#] = Sources tab.
A4: Parameter | B4: Value | C4: Unit | D4: Low | E4: High | F4: Confidence | G4: Source / rationale
A5: General
A6: USD/INR exchange rate | B6: 96 | C6: ₹ per USD | D6: 95.5 | E6: 96.1 | F6: Researched | G6: [S1] 95.96 on 25-Sep-2026.
A7: RUNNING DAYS – drive capacity, labour and power (change these to test)
A8: Packhouse (grading/packing lines) running days per year | B8: 300 | C8: days/yr | D8: 250 | E8: 330 | F8: User | G8: Sitpur DPR design basis: 25 MT/day × ~300 operating days. Staggered banana planting keeps the line fed; ~65 days lost to Sundays/festivals/monsoon/maintenance.
A9: Pre-cooling running days per year | B9: 300 | C9: days/yr | D9: 250 | E9: 330 | F9: Estimate | G9: Runs whenever the packhouse packs fruit (same days as packhouse).
A10: Cold storage running days per year | B10: 330 | C10: days/yr | D10: 300 | E10: 365 | F10: Estimate | G10: Holds stock between packing and dispatch and during container build-up, so runs a little longer than the line; ~35 days shutdown for defrost/maintenance/lean weeks.
A11: Banana line intake capacity | B11: 25 | C11: t/day | D11: 20 | E11: 30 | F11: User | G11: Sitpur DPR: 25 MT/day design intake (planning figure).
A12: Multi-fruit line (papaya & mango) intake capacity | B12: 8 | C12: t/day | D12: 5 | E12: 12 | F12: Estimate | G12: Separate sorting/washing/sizing tables – papaya & mango are handled whole, not de-handed.
A13: Forced-air pre-cooling units | B13: 3 | C13: units | D13: 2 | E13: 4 | F13: Derived | G13: Sized in 'Operations & Capacity' – 3 × 6 MT covers banana + papaya/mango peaks.
A14: Pre-cooling batch size per unit | B14: 6 | C14: MT/batch | F14: Researched | G14: [S22] MIDH norm unit = 6 MT.
A15: Pre-cooling batches per unit per day | B15: 2 | C15: batches/day | D15: 2 | E15: 3 | F15: Estimate | G15: 6–8 h forced-air cycle.
A16: Cold storage capacity (2 chambers × 50 MT, 13 °C) | B16: 100 | C16: MT | D16: 50 | E16: 150 | F16: Derived | G16: Two chambers so ethylene-producing papaya/mango never share air with green banana. DPR had 20–25 MT – too small once export containers (20 t each) are staged.
A17: Average cold-storage holding – banana | B17: 2 | C17: days | D17: 1 | E17: 4 | F17: Estimate
A18: Average cold-storage holding – papaya | B18: 3 | C18: days | D18: 2 | E18: 7 | F18: Estimate
A19: Average cold-storage holding – mango | B19: 4 | C19: days | D19: 2 | E19: 10 | F19: Estimate
A20: Farm – Sitpur Estate, Dabhoi (owner business plan, Sep-2026)
A21: Area under banana | B21: 150 | C21: acres | F21: User | G21: Farm plan.
A22: Plants per acre (6 ft × 6 ft) | B22: 1200 | C22: plants/acre | D22: 1200 | E22: 1452 | F22: User | G22: Farm plan. Research: 1,200–1,450 [S2].
A23: Yield per plant – plant crop | B23: 25 | C23: kg/plant | D23: 20 | E23: 30 | F23: User | G23: Farm plan ('minimum'). = 30 t/acre; Gujarat avg 26.7 t/acre [S4].
A24: Yield per plant – ratoon | B24: 25 | C24: kg/plant | D24: 18 | E24: 25 | F24: User | G24: Farm plan. Plan itself flags ratoon bunches are often lighter – test ~20 kg.
A25: Plant-crop months (planting → harvest) | B25: 11 | C25: months | D25: 11 | E25: 13 | F25: User | G25: Farm plan.
A26: Ratoon months | B26: 8 | C26: months | D26: 8 | E26: 10 | F26: User | G26: Farm plan (19-month cycle, then replant).
A27: Inputs per plant – plant crop (plant, fertiliser, pesticide, labour) | B27: 125 | C27: ₹/plant | F27: User | G27: Farm plan (plant material ₹17–20 included).
A28: Inputs per plant – ratoon | B28: 50 | C28: ₹/plant | F28: User | G28: Farm plan.
A29: Land rent (opportunity cost) | B29: 50000 | C29: ₹/acre/yr | D29: 30000 | E29: 80000 | F29: User | G29: Farm plan; research range ₹30,000–80,000 [S5].
A30: Farm-gate price – plant crop (used for surplus sold unprocessed) | B30: 15 | C30: ₹/kg | D30: 8 | E30: 21 | F30: User | G30: Farm plan; your draft ₹11–21 seasonal.
A31: Farm-gate price – ratoon | B31: 12 | C31: ₹/kg | D31: 8 | E31: 20 | F31: User | G31: Farm plan.
A32: SCENARIO: banana yield shortfall this season | B32: 0 | C32: % of yield | D32: 0 | E32: 0.5 | F32: Scenario | G32: Set e.g. 30% to test a bad season (disease, wind, heat).
A33: SCENARIO: acres switched to rotation crop | B33: 0 | C33: acres | D33: 0 | E33: 150 | F33: Scenario | G33: Acres taken out of banana this year and planted with the crop chosen on 'Crop Rotation'.
A34: Rotation crop chosen (1 = Papaya, 2 = Watermelon, 3 = Green manure) | B34: 1 | C34: choice | D34: 1 | E34: 3 | F34: Derived | G34: Papaya recommended – see 'Crop Rotation'.
A35: LABOUR – daily-wage cap
A36: Upper limit – loading/unloading & harvest labour | B36: 1000 | C36: ₹/person/day | F36: User | G36: Your instruction: never above ₹1,000/day. All harvest & loading wages below are capped with MIN(rate, cap).
A37: Harvest tonnes per crew-day | B37: 13 | C37: t/crew-day | F37: User | G37: Your note: 13 t needs 10 people + 3 harvesters.
A38: Harvest carriers / handlers per crew | B38: 10 | C38: people | F38: User | G38: Your note.
A39: Harvesters (bunch cutters) per crew | B39: 3 | C39: people | F39: User | G39: Your note.
A40: Harvest wage asked | B40: 1000 | C40: ₹/person/day | F40: User | G40: Your note – at the cap.
A41: Loading / unloading crew at packhouse | B41: 8 | C41: people/day | D41: 6 | E41: 12 | F41: Estimate | G41: Unloading field crates & procured fruit, loading reefer trucks/containers.
A42: Loading/unloading wage asked | B42: 800 | C42: ₹/person/day | D42: 600 | E42: 1000 | F42: Estimate | G42: Hamali rates; capped at ₹1,000.
A43: Banana line workers per running day | B43: 30 | C43: people | D43: 25 | E43: 40 | F43: Estimate | G43: De-handing, washing, fungicide dip, grading, packing.
A44: Multi-fruit line workers per running day | B44: 12 | C44: people | D44: 8 | E44: 16 | F44: Estimate | G44: Sorting, washing, wrapping (papaya), sizing, packing.
A45: Packhouse worker wage | B45: 512.5 | C45: ₹/day | D45: 501.5 | E45: 600 | F45: Researched | G45: [S6] Gujarat Zone-I unskilled minimum wage Apr–Sep 2026.
A46: Statutory loading on salaries | B46: 0.13 | C46: % of salary | D46: 0.12 | E46: 0.2 | F46: Estimate
A47: ENERGY
A48: Effective electricity tariff | B48: 8.5 | C48: ₹/kWh | D48: 7.5 | E48: 9 | F48: Researched | G48: [S13] ₹7.5–8.5/kWh effective + DG backup.
A49: Packing lines connected load | B49: 30 | C49: kW | D49: 20 | E49: 45 | F49: Estimate | G49: Conveyors, pumps, sizer, lights, sealing.
A50: Line running hours per day | B50: 10 | C50: h/day | D50: 8 | E50: 16 | F50: Estimate
A51: Line load factor | B51: 0.6 | C51: % | D51: 0.5 | E51: 0.8 | F51: Estimate
A52: Pre-cooling energy per tonne cooled (30 → 13 °C) | B52: 20 | C52: kWh/t | D52: 15 | E52: 30 | F52: Derived | G52: ~17 kWh(thermal)/t field heat; forced-air fans + COP ≈ 20 kWh(e)/t.
A53: Pre-cooling standby / fans per unit per running day | B53: 10 | C53: kWh/unit/day | D53: 5 | E53: 20 | F53: Estimate
A54: Cold storage energy per MT capacity per running day (13 °C) | B54: 3 | C54: kWh/MT/day | D54: 2 | E54: 5 | F54: Derived | G54: [S33] 60–70 W/m³ cooling duty at ~2.2–3.4 m³/t, ~50% compressor duty in Vadodara heat.
A55: Contract demand | B55: 200 | C55: kW | D55: 150 | E55: 250 | F55: Estimate | G55: 3 pre-cooling units + 2 chambers + lines.
A56: Demand/fixed charge | B56: 150 | C56: ₹/kW/month | D56: 85 | E56: 250 | F56: Estimate | G56: [S13] LTMD fixed charges ₹50–85/kW for first 40 kW, higher slabs above.
A57: Banana post-harvest & packing
A58: Stalk / rachis share of bunch | B58: 0.08 | C58: % of bunch | D58: 0.06 | E58: 0.12 | F58: Estimate
A59: Banana culls / B-grade | B59: 0.1 | C59: % of fruit | D59: 0.05 | E59: 0.15 | F59: Derived | G59: Premium-only grading; culls → banana flour.
A60: Pre-cooling & handling weight loss | B60: 0.015 | C60: % of graded fruit | D60: 0.01 | E60: 0.03 | F60: Estimate
A61: Banana export share of sellable | B61: 0.25 | C61: % | F61: User | G61: Your brief (DPR suggests export only from Phase 2).
A62: Banana carton net weight | B62: 13 | C62: kg | D62: 13 | E62: 13.5 | F62: Researched | G62: [S9][S10]
A63: Cartons per 40' HC reefer | B63: 1540 | C63: cartons | D63: 1400 | E63: 1540 | F63: Researched | G63: [S11]
A64: Pseudostem fresh weight per plant | B64: 30 | C64: kg/plant | D64: 20 | E64: 40 | F64: Derived | G64: [S12]
A65: Post-harvest chemicals & sanitation (all fruits) | B65: 0.4 | C65: ₹/kg fruit | D65: 0.3 | E65: 0.6 | F65: User | G65: Your draft.
A66: Process water & wash-water treatment | B66: 0.05 | C66: ₹/kg fruit | D66: 0.03 | E66: 0.1 | F66: Estimate
A67: Banana export carton (13 kg telescopic) | B67: 84 | C67: ₹/carton | D67: 75 | E67: 95 | F67: Researched | G67: [S9]
A68: Export polyliner / Banavac | B68: 7 | C68: ₹/carton | D68: 5 | E68: 10 | F68: Estimate
A69: Export cushion pad | B69: 4 | C69: ₹/carton | D69: 3 | E69: 6 | F69: Estimate
A70: Export labels & stickers | B70: 3 | C70: ₹/carton | D70: 2 | E70: 5 | F70: Estimate
A71: Banana domestic premium carton (13 kg) | B71: 60 | C71: ₹/carton | D71: 50 | E71: 84 | F71: Estimate
A72: Domestic liner | B72: 5 | C72: ₹/carton | D72: 3 | E72: 7 | F72: Estimate
A73: Domestic labels | B73: 2 | C73: ₹/carton | D73: 1 | E73: 4 | F73: Estimate
A74: Papaya (procured from Vadodara/Anand growers)
A75: Papaya intake on papaya days | B75: 6 | C75: t/day | D75: 3 | E75: 8 | F75: Estimate | G75: Anand & Vadodara have the largest papaya area in Middle Gujarat [S34].
A76: Papaya packing days (Jul–Mar, outside mango season) | B76: 240 | C76: days/yr | D76: 150 | E76: 270 | F76: Estimate | G76: Papaya is available almost year-round in Gujarat; line switches to mango Apr–Jun.
A77: Papaya procurement price (A-grade, farm-gate) | B77: 12 | C77: ₹/kg | D77: 10 | E77: 20 | F77: Researched | G77: [S34] Gujarat ₹10/kg (Feb-2026); Red Lady ₹20/kg Navsari (May-2026).
A78: Collection freight to Sitpur | B78: 1 | C78: ₹/kg | D78: 0.5 | E78: 1.5 | F78: Estimate | G78: ≤60 km collection run.
A79: Papaya culls at grading | B79: 0.12 | C79: % of intake | D79: 0.08 | E79: 0.2 | F79: Estimate | G79: Culls → compost.
A80: Papaya selling price – graded, pre-cooled, cartoned, delivered | B80: 26 | C80: ₹/kg | D80: 20 | E80: 32 | F80: Derived | G80: [S35] BigBasket papaya ₹61–81/kg retail; premium B2B ~40–45% of retail.
A81: Papaya carton net weight | B81: 10 | C81: kg | F81: Estimate
A82: Papaya returnable plastic crate – hire per trip (10 kg) | B82: 10 | C82: ₹/crate | D82: 6 | E82: 45 | F82: Estimate | G82: Modern-trade DCs take papaya in returnable crates; a 5-ply carton would cost ~₹30–45 [S36].
A83: Papaya foam nets / paper wrap per crate | B83: 10 | C83: ₹/crate | D83: 6 | E83: 14 | F83: Estimate
A84: Kesar mango (procured Apr–Jun from Valsad/Navsari/Gir growers)
A85: Mango intake on mango days | B85: 6 | C85: t/day | D85: 3 | E85: 8 | F85: Estimate
A86: Mango packing days | B86: 60 | C86: days/yr | D86: 45 | E86: 75 | F86: Researched | G86: [S37] Kesar arrives April; main Gir season May–June.
A87: Mango procurement price | B87: 70 | C87: ₹/kg | D87: 40 | E87: 133 | F87: Researched | G87: [S38] Talala APMC ₹70–75/kg (late Apr-2026); grades ₹40–133/kg.
A88: Inbound freight (150–400 km) | B88: 3 | C88: ₹/kg | D88: 2 | E88: 5 | F88: Estimate
A89: Mango culls at grading | B89: 0.08 | C89: % of intake | D89: 0.05 | E89: 0.15 | F89: Estimate | G89: Culls → compost (pulp units may buy – price not verified).
A90: Mango selling price – graded, pre-cooled, boxed, delivered | B90: 120 | C90: ₹/kg | D90: 90 | E90: 150 | F90: Derived | G90: [S38] dealer 10 kg boxes ₹140–150/kg; [S35] BigBasket Kesar ₹407/kg retail.
A91: Mango box net weight | B91: 3 | C91: kg | D91: 3 | E91: 5 | F91: Estimate | G91: Premium retail/quick-commerce pack.
A92: Mango 3 kg printed box | B92: 30 | C92: ₹/box | D92: 15 | E92: 45 | F92: Researched | G92: [S36] mango corrugated boxes ₹15–45/piece.
A93: Mango tissue/filler/label per box | B93: 5 | C93: ₹/box | D93: 3 | E93: 8 | F93: Estimate
A94: Export chain – banana (per 40' HC reefer)
A95: Banana export price, CIF Gulf | B95: 7 | C95: US$ per 13 kg carton | D95: 5.5 | E95: 9 | F95: Derived | G95: [S14][S15][S16]
A96: Reefer haulage Sitpur → port (Hazira ~170 km / Nhava Sheva / Mundra) | B96: 60000 | C96: ₹/container | D96: 35000 | E96: 70000 | F96: User | G96: Your draft (JNPT/Mundra). DPR notes Hazira at ~170 km – could be ~₹35–40k if reefer services suit.
A97: Origin THC, seal, B/L, VGM | B97: 22000 | C97: ₹/container | D97: 18000 | E97: 28000 | F97: Estimate
A98: CHA, customs, phyto, docs | B98: 20000 | C98: ₹/container | D98: 15000 | E98: 25000 | F98: User | G98: Your draft.
A99: Residue test + ethylene absorber + logger | B99: 14000 | C99: ₹/container | D99: 10000 | E99: 18000 | F99: Estimate
A100: Ocean freight 40' reefer (base) | B100: 2000 | C100: US$/container | D100: 1500 | E100: 3000 | F100: Derived | G100: [S17]
A101: Gulf war-risk surcharge | B101: 4000 | C101: US$/reefer | D101: 3500 | E101: 4800 | F101: Researched | G101: [S18][S19]
...

Sheet Farm Plan
A1: Farm economics – Sitpur Estate, 150 acres (from your Banana Farm Business Plan, Sep-2026)
A2: Owner figures are the base case (Confidence = User). Research cross-checks are shown alongside. Harvest labour is costed in 'Packhouse Opex' with the ₹1,000/day cap.
A4: Item | B4: Plant crop | C4: Ratoon | D4: Full cycle / annual | E4: Basis | F4: Research cross-check
A5: A. Per acre (owner plan)
A6: Months | B6: =Inputs!$B$25 -> 11 | C6: =Inputs!$B$26 -> 8 | D6: =B6+C6 -> 19 | E6: 19-month cycle, then replant | F6: [S2] G9 matures 11–12 months in Gujarat
A7: Output (kg/acre) | B7: =Inputs!$B$22*Inputs!$B$23*(1-Inputs!$B$32) -> 30000 | C7: =Inputs!$B$22*Inputs!$B$24*(1-Inputs!$B$32) -> 30000 | D7: =B7+C7 -> 60000 | E7: Plants × kg/plant × (1 − shortfall) | F7: [S4] Gujarat avg 26.7 t/acre; Bharuch 29.4 t/acre
A8: Inputs (₹/acre) | B8: =Inputs!$B$22*Inputs!$B$27 -> 150000 | C8: =Inputs!$B$22*Inputs!$B$28 -> 60000 | D8: =B8+C8 -> 210000 | E8: ₹125 / ₹50 per plant (plant, fertiliser, pesticide, labour) | F8: Researched itemised build-up (v1 of this workbook) gave ₹1.64 L plant crop excl. rent – plan's ₹1.5 L is consistent
A9: Farm-gate value (₹/acre) – reference only | B9: =B7*Inputs!$B$30 -> 450000 | C9: =C7*Inputs!$B$31 -> 360000 | D9: =B9+C9 -> 810000 | E9: What the fruit is worth if sold at farm gate
A10: Plan's harvest handling ₹10/plant (NOT used – see note) | B10: =Inputs!$B$22*10 -> 12000 | C10: =Inputs!$B$22*10 -> 12000 | E10: Replaced by your crew model (13 people/13 t, ≤₹1,000/day) = ~₹1/kg vs ₹0.40/kg here
A12: B. Annual farm fixed costs (owner plan)
A13: Item | B13: Qty | C13: Rate (₹) | D13: ₹ per year | E13: Basis | F13: Note
A14: Permanent workers already inside ₹125/₹50 per-plant inputs? (1 = yes → exclude below) | B14: 0 | E14: Plan's open question; base case counts them
A15: Land rent | B15: =Inputs!$B$21 -> 150 | C15: =Inputs!$B$29 -> 50000 | D15: =B15*C15 -> 7500000 | E15: 150 acres × ₹50,000 | F15: Opportunity cost if owners farm it
A16: Farm workers (50 × 312 paid days) | B16: 50 | C16: 400 | D16: =IF($B$14=1,0,B16*C16*312) -> 6240000 | E16: ₹400/day | F16: Below Gujarat minimum wage (₹501–512/day, [S6]) – check
A17: Agronomist / farm manager | B17: 1 | C17: 60000 | D17: =B17*C17*12 -> 720000 | E17: ₹/month
A18: Sub-assistants | B18: 2 | C18: 25000 | D18: =B18*C18*12 -> 600000 | E18: ₹/month
A19: GAS – salary | B19: 1 | C19: 25000 | D19: =B19*C19*12 -> 300000 | E19: ₹/month
A20: HAS – salary | B20: 1 | C20: 25000 | D20: =B20*C20*12 -> 300000 | E20: ₹/month
A21: Company driver | B21: 1 | C21: 18000 | D21: =B21*C21*12 -> 216000 | E21: ₹/month
A22: MGVCL power, 9 connections | B22: 9 | C22: 30000 | D22: =B22*C22 -> 270000 | E22: ₹/connection/yr
A23: Fuel – tractors | B23: 1 | C23: 1200000 | D23: =B23*C23 -> 1200000 | E23: ₹/yr
A24: Fuel – car & 3 bikes | B24: 12 | C24: 29000 | D24: =B24*C24 -> 348000 | E24: ₹/month
A25: Repairs & maintenance | B25: 1 | C25: 300000 | D25: =B25*C25 -> 300000 | E25: ₹/yr
A26: Insurance – vehicles, assets, staff accident | B26: 1 | C26: 400000 | D26: =B26*C26 -> 400000 | E26: ₹/yr
A27: Crop insurance (5% of ₹1.5 L/acre) | B27: =Inputs!$B$21 -> 150 | C27: 7500 | D27: =B27*C27 -> 1125000 | E27: ₹/acre/yr | F27: Gujarat exited PMFBY – private/state policy quote needed
A28: Total farm fixed costs | D28: =SUM(D15:D27) -> 19519000 | E28: Plan: ₹195.19 L
A30: C. Farm capex (owner plan)
A31: Asset | B31: Cost (₹) | C31: Life (yrs) | D31: Depreciation ₹/yr | E31: Note
A32: Tractors: 3 large @ ₹10 L + 3 small @ ₹6 L | B32: 4800000 | C32: 8 | D32: =B32/C32 -> 600000
A33: Drip irrigation @ ₹50,000/acre + headworks | B33: 8000000 | C33: 7 | D33: =B33/C33 -> 1142857.1 | E33: Research: ₹25,000–60,000/acre [S8]
A34: 50-t truck weighbridge incl. civil | B34: 700000 | C34: 10 | D34: =B34/C34 -> 70000
A35: Wild boar / animal fencing | B35: 300000 | C35: 3 | D35: =B35/C35 -> 100000
A36: Total farm capex / depreciation | B36: =SUM(B32:B35) -> 13800000 | D36: =SUM(D32:D35) -> 1912857.1
A38: D. Annual farm summary (banana acres = 150 − rotation acres)
A39: Banana acres this year | D39: =(Inputs!$B$21-Inputs!$B$33) -> 150
A40: Annual banana harvest (t) | D40: =(Inputs!$B$21-Inputs!$B$33)*D7/D6*12/1000 -> 5684.2105
A41: Annual inputs (₹) | D41: =(Inputs!$B$21-Inputs!$B$33)*D8/D6*12 -> 19894737
A42: Annual fixed costs (₹) | D42: =D28 -> 19519000
A43: Farm cash cost (inputs + fixed) (₹) | D43: =D41+D28 -> 39413737
A44: Farm depreciation (₹) | D44: ='Farm Plan'!$D$36 -> 1912857.1
A45: Farm cost per kg of bunch incl. depreciation (₹/kg) | D45: =IF(D40=0,0,(D43+'Farm Plan'!$D$36)/(D40*1000)) -> 7.2704193 | E45: Plan's break-even ₹7.67/kg includes plan harvest handling
A46: Farm-gate value of the harvest (₹) – reference | D46: =(Inputs!$B$21-Inputs!$B$33)*D9/D6*12 -> 76736842
A47: Average farm-gate price (₹/kg) | D47: =IF(D40=0,0,D46/(D40*1000)) -> 13.5

Sheet Crop Rotation
A1: Rotation / backup crop for seasons when banana does not do well
A2: Compared per acre. Land rent is already in farm fixed costs, so margins here are before rent. Pick the crop on Inputs → 'Rotation crop chosen' and set acres to switch.
A4: Item | B4: 1. Papaya (Red Lady 786) | C4: 2. Watermelon (hybrid) | D4: 3. Green manure (sunhemp / dhaincha) | E4: Unit | F4: Sources / notes
A5: Duration in field | B5: 20 | C5: 3 | D5: 2 | E5: months | F5: Papaya fruits from 6–8 months and bears ~2 years [S39]; watermelon 75–90 days [S40]; green manure 45–60 days [S41].
A6: Cultivation cost (excl. land rent) | B6: 80000 | C6: 82844 | D6: =D7+D8 -> 5280 | E6: ₹/acre | F6: [S39] papaya ₹70–90k/acre; [S40] watermelon Banaskantha study ₹2,04,696/ha (cost C2). Green manure computed below.
A7: Green manure: seed 20 kg × price | D7: =20*114 -> 2280 | E7: ₹/acre | F7: [S41] 20 kg/acre; dhaincha seed ₹2,850/25 kg (≈₹114/kg).
A8: Green manure: sowing + incorporation | D8: 3000 | E8: ₹/acre | F8: Estimate (tractor passes).
A9: Yield | B9: 40 | C9: 10 | D9: 0 | E9: t/acre | F9: [S39] papaya 30–50 t/acre over its life; [S40] watermelon 8–12 t/acre.
A10: Farm-gate price | B10: 12 | C10: 7 | D10: 0 | E10: ₹/kg | F10: [S34] papaya ₹10–20/kg Gujarat 2026; [S40] watermelon ₹4–6.25/kg Gujarat mandis (May-2025), +20–30% in 2026 [S42].
A11: Harvest & transport to buyer | B11: 1 | C11: 0.8 | D11: 0 | E11: ₹/kg | F11: Estimate.
A12: Revenue per acre | B12: =B9*1000*B10 -> 480000 | C12: =C9*1000*C10 -> 70000 | D12: =D9*1000*D10 -> 0
A13: Harvest & transport | B13: =B9*1000*B11 -> 40000 | C13: =C9*1000*C11 -> 8000 | D13: =D9*1000*D11 -> 0
A14: Margin per acre per crop (before rent) | B14: =B12-B6-B13 -> 360000 | C14: =C12-C6-C13 -> -20844 | D14: =D12-D6-D13 -> -5280
A15: Margin per acre per month in field | B15: =B14/B5 -> 18000 | C15: =C14/C5 -> -6948 | D15: =D14/D5 -> -2640
A16: Banana benchmark: margin per acre per month (farm-gate value − inputs) | B16: =('Farm Plan'!$D$9-'Farm Plan'!$D$8)/'Farm Plan'!$D$6 -> 31578.947 | F16: From 'Farm Plan' section A (before harvest labour and fixed costs)
A18: Agronomic fit
A19: Breaks the banana disease cycle (Fusarium wilt, nematodes)? | B19: Yes – not a host of Foc [S43] | C19: Yes – cucurbits are among rotation crops shown to cut banana wilt [S43] | D19: Yes – adds organic matter; best done just before replanting
A20: Reuses banana drip, labour & packhouse? | B20: Yes – drip reused; fruit goes through your own multi-fruit line | C20: Partly – drip reused; sold direct (low value/kg for packhouse) | D20: No revenue
A21: Key risk | B21: Papaya ringspot virus (aphids); keep away from cucurbits | C21: Hosts papaya ringspot virus-W – don't grow next to papaya | D21: None
A22: When to use | B22: Main backup: a whole block that fails or needs a 1.5–2 yr break | C22: Quick 3-month filler if a failure is noticed in Dec–Feb, before June replanting | D22: 45–60 days before every banana replant
A24: Scenario feeding the P&L (from Inputs)
A25: Crop chosen | B25: =INDEX(B4:D4,1,Inputs!$B$34) -> 1. Papaya (Red Lady 786)
A26: Acres switched out of banana | B26: =Inputs!$B$33 -> 0
A27: Annualised rotation-crop revenue (₹) | B27: =B26*INDEX(B12:D12,1,Inputs!$B$34)/INDEX(B5:D5,1,Inputs!$B$34)*12 -> 0
A28: Annualised rotation-crop cost (₹) | B28: =B26*(INDEX(B6:D6,1,Inputs!$B$34)+INDEX(B13:D13,1,Inputs!$B$34))/INDEX(B5:D5,1,Inputs!$B$34)*12 -> 0
A29: Recommendation
A30: Use papaya as the backup cash crop, because it is the only option that comes close to banana's margin per acre-month and it feeds your own packhouse. Sow green manure before every banana replant. Use watermelon only as a short filler, and never next to papaya. Rotation cuts Fusarium wilt risk, which the plan lists as a key threat on land that has been under banana since 2010.

Sheet Fruit Selection
A1: Which extra fruits should the packhouse handle? (screening of candidates)
A2: Criteria: supply near Sitpur, season that fills banana gaps, storage compatible with banana's 13–14 °C rooms, value per kg, fit with lines. Blank = not verified.
A4: Fruit | B4: Supply near Sitpur | C4: Season | D4: Storage temp & shelf life | E4: Buy price (₹/kg, 2026) | F4: Premium sale / retail (₹/kg) | G4: Fit with banana packhouse | H4: Verdict
A5: Papaya | B5: Anand & Vadodara have the largest papaya area in Middle Gujarat [S34] | C5: Almost year-round | D5: 10–13 °C; 1–3 weeks; tropical group with banana & mango [S44] | E5: 10–20 [S34] | F5: BigBasket 61–81 retail [S35] | G5: Same 13 °C chamber group; high volume fills idle line capacity | H5: RECOMMENDED
A6: Kesar mango | B6: Valsad/Navsari ~150–200 km; Gir-Talala ~400 km [S37] | C6: Apr–Jun (~60 days) | D6: 12–13 °C; 2–3 weeks; tropical group [S44] | E6: 70–75 APMC; 40–133 by grade [S38] | F6: 140–150 dealer; 407 BigBasket [S35][S38] | G6: Highest value per kg; pre-cooling adds shelf life; short season | H6: RECOMMENDED (seasonal)
A7: Sapota (chikoo) | B7: Navsari/Valsad – India's largest sapota belt, ~150 km [S45] | C7: Most of the year (peak winter) | E7: 7.5–12.5 Valsad APMC [S45] | F7: ~35 Gujarat market [S45] | G7: Low value; ~90% already flows to Delhi via co-ops | H7: Possible later
A8: Pomegranate | B8: Kutch/Banaskantha ~400–450 km [S46] | C8: Main crop in winter | D8: ~5–7 °C – needs its own chamber (standard post-harvest guides) | E8: 30 (A-grade, Kutch) [S46] | F8: 115 wholesale; 132–150 export grade [S46] | G8: Separate cold room; export needs registered farms (Anar-Net); far away | H8: Not now
A9: Watermelon | B9: Mahuva/Bhavnagar & local [S42] | C9: Feb–May | E9: 4–6 [S40] | G9: Bulky, low value per kg – packing adds little | H9: Rotation crop only
A11: Decision: banana + papaya + Kesar mango. All three are tropical, chilling-sensitive fruit stored around 13 °C, so they share pre-cooling. Papaya and mango give off ethylene, which would ripen green banana, so they get their own 50 MT cold chamber. Pomegranate would need a third, colder chamber.
A13: Operating calendar (● = packing that fruit)
A14: Fruit | B14: Jan | C14: Feb | D14: Mar | E14: Apr | F14: May | G14: Jun | H14: Jul | I14: Aug | J14: Sep | K14: Oct | L14: Nov | M14: Dec
A15: Banana | B15: ● | C15: ● | D15: ● | E15: ● | F15: ● | G15: ● | H15: ● | I15: ● | J15: ● | K15: ● | L15: ● | M15: ●
A16: Papaya | B16: ● | C16: ● | D16: ● | H16: ● | I16: ● | J16: ● | K16: ● | L16: ● | M16: ●
A17: Mango | E17: ● | F17: ● | G17: ●

Sheet Operations & Capacity
A1: Operations, running days, capacity & volumes
A2: Everything here recalculates from the running days on Inputs. If days fall, capacity falls and unprocessed banana is sold at farm gate.
A4: Item | B4: Banana | C4: Papaya | D4: Mango | E4: Total | F4: Unit / note
A5: Running days & capacity
A6: Packing days used | B6: =Inputs!$B$8 -> 300 | C6: =MAX(0,MIN(Inputs!$B$76,Inputs!$B$8-D6)) -> 240 | D6: =MIN(Inputs!$B$86,Inputs!$B$8) -> 60 | F6: days/yr – mango gets priority in its season, papaya fills the rest
A7: Line capacity per day | B7: =Inputs!$B$11 -> 25 | C7: =MIN(Inputs!$B$75,Inputs!$B$12) -> 6 | D7: =MIN(Inputs!$B$85,Inputs!$B$12) -> 6 | F7: t/day intake
A8: Line capacity per year | B8: =B6*B7 -> 7500 | C8: =C6*C7 -> 1440 | D8: =D6*D7 -> 360 | F8: t/yr
A9: Intake
A10: Fruit available (banana harvest / planned procurement) | B10: ='Farm Plan'!$D$40 -> 5684.2105 | C10: =Inputs!$B$75*Inputs!$B$76 -> 1440 | D10: =Inputs!$B$85*Inputs!$B$86 -> 360 | F10: t/yr
A11: Processed through packhouse | B11: =MIN(B10,B8) -> 5684.2105 | C11: =MIN(C10,C8) -> 1440 | D11: =MIN(D10,D8) -> 360 | E11: =SUM(B11:D11) -> 7484.2105 | F11: t/yr
A12: Banana not processed → sold at farm gate | B12: =B10-B11 -> 0 | F12: t/yr – rises if you cut running days
A13: Line utilisation | B13: =IF(B8=0,0,B11/B8) -> 0.75789474 | C13: =IF(C8=0,0,C11/C8) -> 1 | D13: =IF(D8=0,0,D11/D8) -> 1 | F13: %
A14: Mass balance
A15: Stalk / rachis removed | B15: =B11*Inputs!$B$58 -> 454.73684 | C15: 0 | D15: 0 | E15: =SUM(B15:D15) -> 454.73684 | F15: t/yr → compost
A16: Fruit after de-handing / receiving | B16: =B11-B15 -> 5229.4737 | C16: =C11 -> 1440 | D16: =D11 -> 360 | E16: =SUM(B16:D16) -> 7029.4737 | F16: t/yr
A17: Culls / B-grade | B17: =B16*Inputs!$B$59 -> 522.94737 | C17: =C16*Inputs!$B$79 -> 172.8 | D17: =D16*Inputs!$B$89 -> 28.8 | E17: =SUM(B17:D17) -> 724.54737 | F17: t/yr → banana flour; papaya & mango → compost
A18: Graded fruit to pre-cooling | B18: =B16-B17 -> 4706.5263 | C18: =C16-C17 -> 1267.2 | D18: =D16-D17 -> 331.2 | E18: =SUM(B18:D18) -> 6304.9263 | F18: t/yr
A19: Sellable packed fruit | B19: =B18*(1-Inputs!$B$60) -> 4635.9284 | C19: =C18*(1-Inputs!$B$60) -> 1248.192 | D19: =D18*(1-Inputs!$B$60) -> 326.232 | E19: =SUM(B19:D19) -> 6210.3524 | F19: t/yr
A20: of which export | B20: =B19*Inputs!$B$61 -> 1158.9821 | C20: 0 | D20: 0 | E20: =SUM(B20:D20) -> 1158.9821 | F20: t/yr
A21: of which domestic premium | B21: =B19-B20 -> 3476.9463 | C21: =C19 -> 1248.192 | D21: =D19 -> 326.232 | E21: =SUM(B21:D21) -> 5051.3703 | F21: t/yr
A22: Cartons / boxes | B22: =B19*1000/Inputs!$B$62 -> 356609.88 | C22: =C19*1000/Inputs!$B$81 -> 124819.2 | D22: =D19*1000/Inputs!$B$91 -> 108744 | E22: =SUM(B22:D22) -> 590173.08 | F22: per year
A23: Export containers (40' HC) | B23: =B20*1000/(Inputs!$B$62*Inputs!$B$63) -> 57.891214 | F23: per year
A24: Domestic reefer trips | B24: =B21*1000/Inputs!$B$109 -> 386.32737 | C24: =C21*1000/Inputs!$B$109 -> 138.688 | D24: =D21*1000/Inputs!$B$109 -> 36.248 | E24: =SUM(B24:D24) -> 561.26337 | F24: per year
A25: Pseudostem biomass (whole harvest) | B25: =(Inputs!$B$21-Inputs!$B$33)*Inputs!$B$22*Inputs!$B$64*24/(Inputs!$B$25+Inputs!$B$26)/1000 -> 6821.0526 | F25: t/yr
A26: Pre-cooling check
A27: Average pre-cooling load on running days | E27: =E18/Inputs!$B$9 -> 21.016421 | F27: t/day
A28: Pre-cooling capacity | E28: =Inputs!$B$13*Inputs!$B$14*Inputs!$B$15 -> 36 | F28: t/day
A29: Pre-cooling utilisation | E29: =E27/E28 -> 0.58378947 | F29: % – above ~80% means peaks will overflow; add a unit
A30: Cold storage check
A31: Average stock held (t) | B31: =B18*Inputs!$B$17/Inputs!$B$10 -> 28.524402 | C31: =C18*Inputs!$B$18/Inputs!$B$10 -> 11.52 | D31: =D18*Inputs!$B$19/Inputs!$B$10 -> 4.0145455 | E31: =SUM(B31:D31) -> 44.058947 | F31: t – banana chamber vs papaya/mango chamber
A32: Peak stock incl. one export container being built (t) | B32: =B31*1.5+IF(B20>0,Inputs!$B$62*Inputs!$B$63/1000,0) -> 62.806603 | C32: =C31*1.5 -> 17.28 | D32: =D31*1.5 -> 6.0218182 | E32: =SUM(B32:D32) -> 86.108421 | F32: t (×1.5 peak factor)
A33: Peak utilisation of 100 MT | E33: =E32/Inputs!$B$16 -> 0.86108421 | F33: %
A34: Labour days
A35: Harvest crew-days (whole banana harvest) | B35: ='Farm Plan'!$D$40/Inputs!$B$37 -> 437.24696 | F35: crew-days/yr (13 people each)
A36: Multi-fruit line days | E36: =C6+D6 -> 300 | F36: days/yr

Sheet Packhouse Capex
A1: Capex by cost centre – packhouse lines, PRE-COOLING, COLD STORAGE and common services
A2: Market prices vs MIDH norms; subsidy on the lower of the two. DPR comparison at the bottom.
A4: Item | B4: Qty | C4: Unit | D4: Unit cost (₹) | E4: Amount (₹) | F4: MIDH norm cap (₹) | G4: Subsidy-eligible (₹) | H4: Subsidy (₹) | I4: Life (yrs) | J4: Depreciation (₹/yr) | K4: Confidence | L4: Source / note
A5: A. PACKHOUSE LINES
A6: Integrated banana pack house (PEB shed, de-handing & wash tanks, conveyor, grading, weighing) | B6: 1 | C6: unit | D6: 9000000 | E6: =B6*D6 -> 9000000 | F6: =B6*5000000 -> 5000000 | G6: =IF(ISNUMBER(F6),MIN(E6,F6),0) -> 5000000 | H6: =G6*Inputs!$B$119 -> 1750000 | I6: 15 | J6: =E6/I6 -> 600000 | K6: Researched | L6: [S24] ₹90 L listing; MIDH norm ₹50 L [S22].
A7: Multi-fruit line: sorting tables, washer/brusher, roller sizer, wrapping tables (papaya & mango) | B7: 1 | C7: lot | D7: 1800000 | E7: =B7*D7 -> 1800000 | F7: not eligible | G7: =IF(ISNUMBER(F7),MIN(E7,F7),0) -> 0 | H7: =G7*Inputs!$B$119 -> 0 | I7: 10 | J7: =E7/I7 -> 180000 | K7: Estimate | L7: Get vendor quotes.
A8: Plastic field crates (banana + papaya + mango) | B8: 3000 | C8: crates | D8: 350 | E8: =B8*D8 -> 1050000 | F8: not eligible | G8: =IF(ISNUMBER(F8),MIN(E8,F8),0) -> 0 | H8: =G8*Inputs!$B$119 -> 0 | I8: 4 | J8: =E8/I8 -> 262500 | K8: Estimate
A9: Material handling: pallet trucks, scales, carton sealing | B9: 1 | C9: lot | D9: 400000 | E9: =B9*D9 -> 400000 | F9: not eligible | G9: =IF(ISNUMBER(F9),MIN(E9,F9),0) -> 0 | H9: =G9*Inputs!$B$119 -> 0 | I9: 7 | J9: =E9/I9 -> 57142.857 | K9: Estimate
A10: Subtotal – Packhouse Lines | E10: =SUM(E6:E9) -> 12250000 | G10: =SUM(G6:G9) -> 5000000 | H10: =SUM(H6:H9) -> 1750000 | J10: =SUM(J6:J9) -> 1099642.9
A11: B. PRE-COOLING
A12: Forced-air pre-cooling units, 6 MT/batch | B12: =Inputs!$B$13 -> 3 | C12: unit | D12: 3000000 | E12: =B12*D12 -> 9000000 | F12: =B12*2500000 -> 7500000 | G12: =IF(ISNUMBER(F12),MIN(E12,F12),0) -> 7500000 | H12: =G12*Inputs!$B$119 -> 2625000 | I12: 10 | J12: =E12/I12 -> 900000 | K12: Derived | L12: MIDH norm ₹25 L per 6 MT unit [S22]; market ~20% above.
A13: Subtotal – Pre-Cooling | E13: =SUM(E12:E12) -> 9000000 | G13: =SUM(G12:G12) -> 7500000 | H13: =SUM(H12:H12) -> 2625000 | J13: =SUM(J12:J12) -> 900000
A14: C. COLD STORAGE
A15: Cold chambers at 13 °C (2 × 50 MT, insulated panels, refrigeration) | B15: =Inputs!$B$16 -> 100 | C15: MT | D15: 22000 | E15: =B15*D15 -> 2200000 | F15: =B15*8000 -> 800000 | G15: =IF(ISNUMBER(F15),MIN(E15,F15),0) -> 800000 | H15: =G15*Inputs!$B$119 -> 280000 | I15: 10 | J15: =E15/I15 -> 220000 | K15: Researched | L15: [S25] ₹14–18k/MT at scale; small chambers cost more. MIDH ~₹8,000/MT.
A16: Subtotal – Cold Storage | E16: =SUM(E15:E15) -> 2200000 | G16: =SUM(G15:G15) -> 800000 | H16: =SUM(H15:H15) -> 280000 | J16: =SUM(J15:J15) -> 220000
A17: D. COMMON SERVICES
A18: Site development (3–5 acre carve-out at Sitpur) | B18: 1 | C18: lot | D18: 1000000 | E18: =B18*D18 -> 1000000 | F18: not eligible | G18: =IF(ISNUMBER(F18),MIN(E18,F18),0) -> 0 | H18: =G18*Inputs!$B$119 -> 0 | I18: 20 | J18: =E18/I18 -> 50000 | K18: Estimate | L18: DPR: site within Sitpur Estate.
A19: Electrical: transformer / HT connection, panels | B19: 1 | C19: lot | D19: 1200000 | E19: =B19*D19 -> 1200000 | F19: not eligible | G19: =IF(ISNUMBER(F19),MIN(E19,F19),0) -> 0 | H19: =G19*Inputs!$B$119 -> 0 | I19: 15 | J19: =E19/I19 -> 80000 | K19: Estimate | L19: DPR: 3-phase available at estate office – extension needed.
A20: DG set 160 kVA (backup for refrigeration) | B20: 1 | C20: unit | D20: 1400000 | E20: =B20*D20 -> 1400000 | F20: not eligible | G20: =IF(ISNUMBER(F20),MIN(E20,F20),0) -> 0 | H20: =G20*Inputs!$B$119 -> 0 | I20: 10 | J20: =E20/I20 -> 140000 | K20: Estimate
A21: Water: borewell link, storage, filtration, wash-water treatment | B21: 1 | C21: lot | D21: 800000 | E21: =B21*D21 -> 800000 | F21: not eligible | G21: =IF(ISNUMBER(F21),MIN(E21,F21),0) -> 0 | H21: =G21*Inputs!$B$119 -> 0 | I21: 10 | J21: =E21/I21 -> 80000 | K21: Estimate | L21: DPR: 9 borewells on estate.
A22: QC lab + office & IT | B22: 1 | C22: lot | D22: 300000 | E22: =B22*D22 -> 300000 | F22: not eligible | G22: =IF(ISNUMBER(F22),MIN(E22,F22),0) -> 0 | H22: =G22*Inputs!$B$119 -> 0 | I22: 5 | J22: =E22/I22 -> 60000 | K22: Estimate
A23: Subtotal – Common Services | E23: =SUM(E18:E22) -> 4700000 | G23: =SUM(G18:G22) -> 0 | H23: =SUM(H18:H22) -> 0 | J23: =SUM(J18:J22) -> 410000
A24: Contingency & pre-operative (5%) – common | B24: 0.05 | E24: =(E10+E13+E16+E23)*B24 -> 1407500 | G24: 0 | H24: 0 | I24: 10 | J24: =E24/I24 -> 140750
A25: TOTAL PROJECT COST | E25: =E10+E13+E16+E23+E24 -> 29557500 | G25: =G10+G13+G16+G23+G24 -> 13300000 | H25: =H10+H13+H16+H23+H24 -> 4655000 | J25: =J10+J13+J16+J23+J24 -> 2770392.9
A27: Financing (AIF + MIDH)
A28: Total project cost (₹) | B28: =E25 -> 29557500
A29: Promoter equity (₹) | B29: =B28*Inputs!$B$120 -> 7389375
A30: Term loan (₹) | B30: =B28-B29 -> 22168125
A31: MIDH subsidy adjusted against loan (₹) | B31: =H25 -> 4655000
A32: Net loan to service (₹) | B32: =B30-B31 -> 17513125
A33: Effective rate after AIF subvention | B33: =(MIN(B32,Inputs!$B$123)*(Inputs!$B$121-Inputs!$B$122)+MAX(0,B32-Inputs!$B$123)*Inputs!$B$121)/B32 -> 0.075
A34: Annual EMI (₹) | B34: =PMT(B33,Inputs!$B$124,-B32) -> 3306483.5
A35: Average annual interest (₹) | B35: =(B34*Inputs!$B$124-B32)/Inputs!$B$124 -> 804608.52
A37: Comparison with your Sitpur DPR (₹ lakh)
A38: DPR line | B38: DPR ₹ L | C38: This model ₹ L | D38: Comment
A39: Civil works + grading/sorting/packing line | B39: 68 | C39: =('Packhouse Capex'!$E$10)/100000 -> 122.5 | D39: Model uses a ₹90 L integrated packhouse listing + multi-fruit line
A40: Ripening chamber (20–25 MT) | B40: 45 | C40: 0 | D40: Not in model – you sell green, pre-ripened fruit. Add back if you ripen for quick-commerce.
A41: Pre-cooling unit & cold storage (20–25 MT) | B41: 28 | C41: =('Packhouse Capex'!$E$13+'Packhouse Capex'!$E$16)/100000 -> 112 | D41: Model: 3 × 6 MT pre-cooling + 100 MT cold storage (multi-fruit + export staging)
A42: Utilities & support | B42: 8 | C42: =('Packhouse Capex'!$E$23)/100000 -> 47
A43: Collection vehicles & material handling | B43: 15 | C43: 0 | D43: Model hires collection transport (₹/kg) instead
A44: Preliminary & pre-operative | B44: 8 | C44: =('Packhouse Capex'!$E$24)/100000 -> 14.075
A45: Total | B45: =SUM(B39:B44) -> 172 | C45: =SUM(C39:C44) -> 295.575

Sheet Packhouse Opex
A1: Opex by cost centre – packhouse lines, PRE-COOLING, COLD STORAGE, common (all driven by running days)
A2: Change running days on Inputs: day-based labour and energy move with them. Wages for harvest/loading are capped at ₹1,000/day.
A4: Item | B4: Driver | C4: Driver unit | D4: Rate | E4: Rate unit | F4: Annual cost (₹) | G4: Cost centre | H4: Confidence | I4: Note
A5: Variable / day-driven
A6: Harvest crew (13 people per 13 t) | B6: ='Operations & Capacity'!$B$35 -> 437.24696 | C6: crew-days | D6: =(Inputs!$B$38+Inputs!$B$39)*MIN(Inputs!$B$40,Inputs!$B$36) -> 13000 | E6: ₹/crew-day (capped) | F6: =B6*D6 -> 5684210.5 | G6: Harvest | H6: User | I6: Whole banana harvest
A7: Loading / unloading crew | B7: =Inputs!$B$8 -> 300 | C7: running days | D7: =Inputs!$B$41*MIN(Inputs!$B$42,Inputs!$B$36) -> 6400 | E7: ₹/day (capped) | F7: =B7*D7 -> 1920000 | G7: Packhouse | H7: Estimate
A8: Banana line workers | B8: ='Operations & Capacity'!$B$6 -> 300 | C8: running days | D8: =Inputs!$B$43*Inputs!$B$45 -> 15375 | E8: ₹/day | F8: =B8*D8 -> 4612500 | G8: Packhouse | H8: Researched | I8: [S6]
A9: Multi-fruit line workers | B9: ='Operations & Capacity'!$E$36 -> 300 | C9: line days | D9: =Inputs!$B$44*Inputs!$B$45 -> 6150 | E9: ₹/day | F9: =B9*D9 -> 1845000 | G9: Packhouse | H9: Researched | I9: [S6]
A10: Chemicals, sanitation & water | B10: ='Operations & Capacity'!$E$16*1000 -> 7029473.7 | C10: kg fruit | D10: =Inputs!$B$65+Inputs!$B$66 -> 0.45 | E10: ₹/kg | F10: =B10*D10 -> 3163263.2 | G10: Packhouse | H10: User/Est.
A11: Packing-line power | B11: =Inputs!$B$8 -> 300 | C11: running days | D11: =Inputs!$B$49*Inputs!$B$50*Inputs!$B$51*Inputs!$B$48 -> 1530 | E11: ₹/day | F11: =B11*D11 -> 459000 | G11: Packhouse | H11: Estimate
A12: PRE-COOLING power – product load | B12: ='Operations & Capacity'!$E$18 -> 6304.9263 | C12: t cooled | D12: =Inputs!$B$52*Inputs!$B$48 -> 170 | E12: ₹/t | F12: =B12*D12 -> 1071837.5 | G12: Pre-cooling | H12: Derived
A13: PRE-COOLING power – fans/standby | B13: =Inputs!$B$9 -> 300 | C13: running days | D13: =Inputs!$B$13*Inputs!$B$53*Inputs!$B$48 -> 255 | E13: ₹/day | F13: =B13*D13 -> 76500 | G13: Pre-cooling | H13: Estimate
A14: COLD STORAGE power | B14: =Inputs!$B$10 -> 330 | C14: running days | D14: =Inputs!$B$16*Inputs!$B$54*Inputs!$B$48 -> 2550 | E14: ₹/day | F14: =B14*D14 -> 841500 | G14: Cold storage | H14: Derived | I14: [S33]
A15: Fixed
A16: Packhouse manager (1) | B16: 1 | C16: headcount | D16: =60000*12*(1+Inputs!$B$46) -> 813600 | E16: ₹/yr incl. statutory | F16: =B16*D16 -> 813600 | G16: Packhouse | H16: Estimate
A17: QA / food safety & documentation (1) | B17: 1 | C17: headcount | D17: =35000*12*(1+Inputs!$B$46) -> 474600 | E17: ₹/yr incl. statutory | F17: =B17*D17 -> 474600 | G17: Packhouse | H17: Estimate
A18: Shift / labour supervisors (2) | B18: 2 | C18: headcount | D18: =25000*12*(1+Inputs!$B$46) -> 339000 | E18: ₹/yr incl. statutory | F18: =B18*D18 -> 678000 | G18: Packhouse | H18: Estimate
A19: Pre-cooling operator (1) | B19: 1 | C19: headcount | D19: =22000*12*(1+Inputs!$B$46) -> 298320 | E19: ₹/yr incl. statutory | F19: =B19*D19 -> 298320 | G19: Pre-cooling | H19: Estimate
A20: Cold storage / refrigeration technician (2) | B20: 2 | C20: headcount | D20: =22000*12*(1+Inputs!$B$46) -> 298320 | E20: ₹/yr incl. statutory | F20: =B20*D20 -> 596640 | G20: Cold storage | H20: Estimate
A21: Accounts & admin (1) | B21: 1 | C21: headcount | D21: =25000*12*(1+Inputs!$B$46) -> 339000 | E21: ₹/yr incl. statutory | F21: =B21*D21 -> 339000 | G21: Common | H21: Estimate
A22: Security guards (3) | B22: 3 | C22: headcount | D22: =14000*12*(1+Inputs!$B$46) -> 189840 | E22: ₹/yr incl. statutory | F22: =B22*D22 -> 569520 | G22: Common | H22: Estimate
A23: Sales / key-account manager (1) | B23: 1 | C23: headcount | D23: =60000*12*(1+Inputs!$B$46) -> 813600 | E23: ₹/yr incl. statutory | F23: =B23*D23 -> 813600 | G23: Common | H23: Estimate
A24: Electricity demand charges | B24: =Inputs!$B$55 -> 200 | C24: kW | D24: =Inputs!$B$56*12 -> 1800 | E24: ₹/kW/yr | F24: =B24*D24 -> 360000 | G24: Common | H24: Estimate
A25: R&M – packhouse lines | B25: ='Packhouse Capex'!$E$10 -> 12250000 | C25: ₹ capex | D25: 0.02 | E25: % of capex | F25: =B25*D25 -> 245000 | G25: Packhouse | H25: Estimate | I25: Refrigeration needs more upkeep
A26: R&M – pre-cooling | B26: ='Packhouse Capex'!$E$13 -> 9000000 | C26: ₹ capex | D26: 0.04 | E26: % of capex | F26: =B26*D26 -> 360000 | G26: Pre-cooling | H26: Estimate | I26: Refrigeration needs more upkeep
A27: R&M – cold storage | B27: ='Packhouse Capex'!$E$16 -> 2200000 | C27: ₹ capex | D27: 0.04 | E27: % of capex | F27: =B27*D27 -> 88000 | G27: Cold storage | H27: Estimate | I27: Refrigeration needs more upkeep
A28: R&M – common services | B28: ='Packhouse Capex'!$E$23 -> 4700000 | C28: ₹ capex | D28: 0.02 | E28: % of capex | F28: =B28*D28 -> 94000 | G28: Common | H28: Estimate | I28: Refrigeration needs more upkeep
A29: Insurance (fire, machinery, stock) | B29: ='Packhouse Capex'!$E$25 -> 29557500 | C29: ₹ capex | D29: 0.0035 | E29: % of capex | F29: =B29*D29 -> 103451.25 | G29: Common | H29: Estimate
A30: Certifications: GlobalG.A.P., APEDA, FSSAI | B30: 1 | C30: lot | D30: 350000 | E30: ₹/yr | F30: =B30*D30 -> 350000 | G30: Common | H30: Estimate
A31: Packhouse site lease (4 acres at estate rent) | B31: 4 | C31: acres | D31: =Inputs!$B$29 -> 50000 | E31: ₹/acre/yr | F31: =B31*D31 -> 200000 | G31: Common | H31: Derived | I31: DPR: lease from the family – terms open
A32: Admin overheads | B32: 12 | C32: months | D32: 50000 | E32: ₹/month | F32: =B32*D32 -> 600000 | G32: Common | H32: Estimate
A34: Cost-centre summary
A35: Cost centre | B35: Opex (₹/yr) | C35: Depreciation (₹/yr) | D35: Interest share (₹/yr) | E35: Total (₹/yr) | F35: Tonnes through | G35: ₹ per kg through
A36: Harvest | B36: =SUMIF($G$5:$G$32,"Harvest",$F$5:$F$32) -> 5684210.5 | C36: 0 | D36: 0 | E36: =B36+C36+D36 -> 5684210.5 | F36: ='Farm Plan'!$D$40 -> 5684.2105 | G36: =IF(F36=0,0,E36/(F36*1000)) -> 1
A37: Packhouse | B37: =SUMIF($G$5:$G$32,"Packhouse",$F$5:$F$32) -> 14210963 | C37: ='Packhouse Capex'!$J$10 -> 1099642.9 | D37: ='Packhouse Capex'!$B$35*('Packhouse Capex'!$E$10)/'Packhouse Capex'!$E$25 -> 333467.12 | E37: =B37+C37+D37 -> 15644073 | F37: ='Operations & Capacity'!$E$11 -> 7484.2105 | G37: =IF(F37=0,0,E37/(F37*1000)) -> 2.090277
A38: Pre-cooling | B38: =SUMIF($G$5:$G$32,"Pre-cooling",$F$5:$F$32) -> 1806657.5 | C38: ='Packhouse Capex'!$J$13 -> 900000 | D38: ='Packhouse Capex'!$B$35*('Packhouse Capex'!$E$13)/'Packhouse Capex'!$E$25 -> 244996.25 | E38: =B38+C38+D38 -> 2951653.7 | F38: ='Operations & Capacity'!$E$18 -> 6304.9263 | G38: =IF(F38=0,0,E38/(F38*1000)) -> 0.46815039
A39: Cold storage | B39: =SUMIF($G$5:$G$32,"Cold storage",$F$5:$F$32) -> 1526140 | C39: ='Packhouse Capex'!$J$16 -> 220000 | D39: ='Packhouse Capex'!$B$35*('Packhouse Capex'!$E$16)/'Packhouse Capex'!$E$25 -> 59887.973 | E39: =B39+C39+D39 -> 1806028 | F39: ='Operations & Capacity'!$E$18 -> 6304.9263 | G39: =IF(F39=0,0,E39/(F39*1000)) -> 0.28644712
A40: Common | B40: =SUMIF($G$5:$G$32,"Common",$F$5:$F$32) -> 3429571.2 | C40: ='Packhouse Capex'!$J$23+'Packhouse Capex'!$J$24 -> 550750 | D40: ='Packhouse Capex'!$B$35*('Packhouse Capex'!$E$23+'Packhouse Capex'!$E$24)/'Packhouse Capex'!$E$25 -> 166257.18 | E40: =B40+C40+D40 -> 4146578.4 | F40: ='Operations & Capacity'!$E$19 -> 6210.3524 | G40: =IF(F40=0,0,E40/(F40*1000)) -> 0.6676881
A41: TOTAL | B41: =SUM(B36:B40) -> 26657542 | C41: =SUM(C36:C40) -> 2770392.9 | D41: =SUM(D36:D40) -> 804608.52 | E41: =SUM(E36:E40) -> 30232544
A43: The pre-cooling and cold-storage rows above are the full cost of owning and running them: power, operators, repairs, plus their share of depreciation and interest. Rent benchmark if outsourced: ~₹0.30/kg/day [S26].

Sheet Unit Economics
A1: Unit economics per kg of sellable fruit – banana export, banana domestic, papaya, Kesar mango
A2: Line-specific labour goes to its own fruit; pre-cooling, cold storage, loading and common costs are shared per kg. Includes a column per carton.
A4: Line item (₹/kg) | B4: Banana export | C4: Banana domestic | D4: Papaya | E4: Kesar mango | F4: How calculated
A5: Selling price | B5: =Inputs!$B$95*Inputs!$B$6/Inputs!$B$62 -> 51.692308 | C5: =Inputs!$B$108 -> 28 | D5: =Inputs!$B$80 -> 26 | E5: =Inputs!$B$90 -> 120 | F5: Export CIF US$/carton × FX ÷ 13 kg
A6: Variable costs
A7: Fruit cost (own farm incl. farm depreciation / procurement) | B7: ='Farm Plan'!$D$45*('Operations & Capacity'!$B$11/'Operations & Capacity'!$B$19) -> 8.9144159 | C7: ='Farm Plan'!$D$45*('Operations & Capacity'!$B$11/'Operations & Capacity'!$B$19) -> 8.9144159 | D7: =(Inputs!$B$77+Inputs!$B$78)/((1-Inputs!$B$79)*(1-Inputs!$B$60)) -> 14.997693 | E7: =(Inputs!$B$87+Inputs!$B$88)/((1-Inputs!$B$89)*(1-Inputs!$B$60)) -> 80.556169 | F7: Banana: farm ₹/kg bunch × bunch per sellable kg. Others: (buy + inbound) ÷ pack-out
A8: Harvest crew (≤ ₹1,000/day) | B8: ='Packhouse Opex'!$G$36*('Operations & Capacity'!$B$11/'Operations & Capacity'!$B$19) -> 1.2261213 | C8: ='Packhouse Opex'!$G$36*('Operations & Capacity'!$B$11/'Operations & Capacity'!$B$19) -> 1.2261213 | D8: =0 -> 0 | E8: =0 -> 0 | F8: Harvest centre ₹/kg bunch × bunch per sellable kg
A9: Line labour (own line) | B9: =IF(('Operations & Capacity'!$B$19*1000)=0,0,'Packhouse Opex'!$F$8/('Operations & Capacity'!$B$19*1000)) -> 0.99494634 | C9: =IF(('Operations & Capacity'!$B$19*1000)=0,0,'Packhouse Opex'!$F$8/('Operations & Capacity'!$B$19*1000)) -> 0.99494634 | D9: =IF((('Operations & Capacity'!$C$19+'Operations & Capacity'!$D$19)*1000)=0,0,'Packhouse Opex'!$F$9/(('Operations & Capacity'!$C$19+'Operations & Capacity'!$D$19)*1000)) -> 1.1718571 | E9: =IF((('Operations & Capacity'!$C$19+'Operations & Capacity'!$D$19)*1000)=0,0,'Packhouse Opex'!$F$9/(('Operations & Capacity'!$C$19+'Operations & Capacity'!$D$19)*1000)) -> 1.1718571 | F9: Banana line ÷ banana kg; multi-fruit line ÷ papaya+mango kg
A10: Loading/unloading, chemicals, line power, packhouse staff & R&M | B10: =(('Packhouse Opex'!$B$37-'Packhouse Opex'!$F$8-'Packhouse Opex'!$F$9)/('Operations & Capacity'!$E$19*1000)) -> 1.2484739 | C10: =(('Packhouse Opex'!$B$37-'Packhouse Opex'!$F$8-'Packhouse Opex'!$F$9)/('Operations & Capacity'!$E$19*1000)) -> 1.2484739 | D10: =(('Packhouse Opex'!$B$37-'Packhouse Opex'!$F$8-'Packhouse Opex'!$F$9)/('Operations & Capacity'!$E$19*1000)) -> 1.2484739 | E10: =(('Packhouse Opex'!$B$37-'Packhouse Opex'!$F$8-'Packhouse Opex'!$F$9)/('Operations & Capacity'!$E$19*1000)) -> 1.2484739 | F10: Rest of packhouse centre opex ÷ all sellable kg
A11: PRE-COOLING (power, operator, R&M) | B11: =('Packhouse Opex'!$B$38/('Operations & Capacity'!$E$19*1000)) -> 0.29091062 | C11: =('Packhouse Opex'!$B$38/('Operations & Capacity'!$E$19*1000)) -> 0.29091062 | D11: =('Packhouse Opex'!$B$38/('Operations & Capacity'!$E$19*1000)) -> 0.29091062 | E11: =('Packhouse Opex'!$B$38/('Operations & Capacity'!$E$19*1000)) -> 0.29091062 | F11: Pre-cooling centre opex ÷ all sellable kg
A12: COLD STORAGE (power, technicians, R&M) | B12: =('Packhouse Opex'!$B$39/('Operations & Capacity'!$E$19*1000)) -> 0.24574129 | C12: =('Packhouse Opex'!$B$39/('Operations & Capacity'!$E$19*1000)) -> 0.24574129 | D12: =('Packhouse Opex'!$B$39/('Operations & Capacity'!$E$19*1000)) -> 0.24574129 | E12: =('Packhouse Opex'!$B$39/('Operations & Capacity'!$E$19*1000)) -> 0.24574129 | F12: Cold-storage centre opex ÷ all sellable kg
A13: Packaging | B13: =(Inputs!$B$67+Inputs!$B$68+Inputs!$B$69+Inputs!$B$70)/Inputs!$B$62 -> 7.5384615 | C13: =(Inputs!$B$71+Inputs!$B$72+Inputs!$B$73)/Inputs!$B$62 -> 5.1538462 | D13: =(Inputs!$B$82+Inputs!$B$83)/Inputs!$B$81 -> 2 | E13: =(Inputs!$B$92+Inputs!$B$93)/Inputs!$B$91 -> 11.666667 | F13: ₹ per box ÷ kg per box
A14: Export residue test & container consumables | B14: =Inputs!$B$99/(Inputs!$B$62*Inputs!$B$63) -> 0.6993007 | C14: =0 -> 0 | D14: =0 -> 0 | E14: =0 -> 0
A15: Transport to port / to domestic buyer | B15: =Inputs!$B$96/(Inputs!$B$62*Inputs!$B$63) -> 2.997003 | C15: =((Inputs!$B$113*Inputs!$B$110+Inputs!$B$114*Inputs!$B$111+Inputs!$B$115*Inputs!$B$112)/Inputs!$B$109) -> 4.7555556 | D15: =(Inputs!$B$110+Inputs!$B$111)/2/Inputs!$B$109 -> 2.8333333 | E15: =((Inputs!$B$113*Inputs!$B$110+Inputs!$B$114*Inputs!$B$111+Inputs!$B$115*Inputs!$B$112)/Inputs!$B$109) -> 4.7555556 | F15: Export haulage; banana & mango use the Ahmedabad/Mumbai/Delhi mix; papaya (short shelf life) goes to Ahmedabad/Mumbai only
A16: Port THC, CHA, customs, phyto | B16: =(Inputs!$B$97+Inputs!$B$98)/(Inputs!$B$62*Inputs!$B$63) -> 2.0979021 | C16: =0 -> 0 | D16: =0 -> 0 | E16: =0 -> 0
A17: Ocean freight (base) | B17: =Inputs!$B$100*Inputs!$B$6/(Inputs!$B$62*Inputs!$B$63) -> 9.5904096 | C17: =0 -> 0 | D17: =0 -> 0 | E17: =0 -> 0
A18: Gulf war-risk surcharge | B18: =Inputs!$B$101*Inputs!$B$102*Inputs!$B$6/(Inputs!$B$62*Inputs!$B$63) -> 19.180819 | C18: =0 -> 0 | D18: =0 -> 0 | E18: =0 -> 0 | F18: Switch on Inputs
A19: Insurance, bank/forex, claims / trade schemes, receivables | B19: =B5*(Inputs!$B$103+Inputs!$B$104+Inputs!$B$105-N(Inputs!$B$106)) -> 2.0935385 | C19: =C5*(Inputs!$B$116+Inputs!$B$121*Inputs!$B$117/365) -> 1.2024658 | D19: =D5*(Inputs!$B$116+Inputs!$B$121*Inputs!$B$117/365) -> 1.1165753 | E19: =E5*(Inputs!$B$116+Inputs!$B$121*Inputs!$B$117/365) -> 5.1534247 | F19: % of price
A20: Total variable cost | B20: =SUM(B7:B19) -> 57.118044 | C20: =SUM(C7:C19) -> 24.032477 | D20: =SUM(D7:D19) -> 23.904584 | E20: =SUM(E7:E19) -> 105.0888
A21: Contribution | B21: =B5-B20 -> -5.4257362 | C21: =C5-C20 -> 3.9675232 | D21: =D5-D20 -> 2.0954157 | E21: =E5-E20 -> 14.911202
A22: Shared fixed & capital costs
A23: Common overheads (admin, security, sales, demand charges, insurance, certifications, site lease) | B23: =('Packhouse Opex'!$B$40/('Operations & Capacity'!$E$19*1000)) -> 0.55223456 | C23: =('Packhouse Opex'!$B$40/('Operations & Capacity'!$E$19*1000)) -> 0.55223456 | D23: =('Packhouse Opex'!$B$40/('Operations & Capacity'!$E$19*1000)) -> 0.55223456 | E23: =('Packhouse Opex'!$B$40/('Operations & Capacity'!$E$19*1000)) -> 0.55223456 | F23: Common centre ÷ all sellable kg
A24: Depreciation & interest – packhouse, pre-cooling, cold storage | B24: =(('Packhouse Opex'!$C$41+'Packhouse Opex'!$D$41)/('Operations & Capacity'!$E$19*1000)) -> 0.57565193 | C24: =(('Packhouse Opex'!$C$41+'Packhouse Opex'!$D$41)/('Operations & Capacity'!$E$19*1000)) -> 0.57565193 | D24: =(('Packhouse Opex'!$C$41+'Packhouse Opex'!$D$41)/('Operations & Capacity'!$E$19*1000)) -> 0.57565193 | E24: =(('Packhouse Opex'!$C$41+'Packhouse Opex'!$D$41)/('Operations & Capacity'!$E$19*1000)) -> 0.57565193 | F24: All centres ÷ all sellable kg
A25: TOTAL COST | B25: =B20+B23+B24 -> 58.24593 | C25: =C20+C23+C24 -> 25.160363 | D25: =D20+D23+D24 -> 25.032471 | E25: =E20+E23+E24 -> 106.21668
A26: NET MARGIN (₹/kg) | B26: =B5-B25 -> -6.5536227 | C26: =C5-C25 -> 2.8396367 | D26: =D5-D25 -> 0.96752918 | E26: =E5-E25 -> 13.783315 | F26: Pre-tax
A27: Net margin % | B27: =IF(B5=0,0,B26/B5) -> -0.12678139 | C27: =IF(C5=0,0,C26/C5) -> 0.1014156 | D27: =IF(D5=0,0,D26/D5) -> 0.037212661 | E27: =IF(E5=0,0,E26/E5) -> 0.11486096
A28: Net margin per box / carton (₹) | B28: =B26*Inputs!$B$62 -> -85.197096 | C28: =C26*Inputs!$B$62 -> 36.915277 | D28: =D26*Inputs!$B$81 -> 9.6752918 | E28: =E26*Inputs!$B$91 -> 41.349945 | F28: 13 kg banana · 10 kg papaya · 3 kg mango
A29: Sellable volume (t/yr) | B29: ='Operations & Capacity'!$B$20 -> 1158.9821 | C29: ='Operations & Capacity'!$B$21 -> 3476.9463 | D29: ='Operations & Capacity'!$C$19 -> 1248.192 | E29: ='Operations & Capacity'!$D$19 -> 326.232
A30: Net margin per year (₹) | B30: =B26*B29*1000 -> -7595531.5 | C30: =C26*C29*1000 -> 9873264.3 | D30: =D26*D29*1000 -> 1207662.2 | E30: =E26*E29*1000 -> 4496558.4
A31: Export breakeven CIF (US$ per 13 kg carton) | B31: =B25*Inputs!$B$62/Inputs!$B$6 -> 7.8874697
A32: Breakeven selling price (₹/kg) | B32: =B25 -> 58.24593 | C32: =C25 -> 25.160363 | D32: =D25 -> 25.032471 | E32: =E25 -> 106.21668
A33: Banana price needed to beat selling at farm gate (₹/kg) | B33: =(('Farm Plan'!$D$47*('Operations & Capacity'!$B$11/'Operations & Capacity'!$B$19))+B25-B7-B8-B19)/(1-(Inputs!$B$103+Inputs!$B$104+Inputs!$B$105-N(Inputs!$B$106)))*Inputs!$B$62/Inputs!$B$6 -> 8.8298853 | C33: =(('Farm Plan'!$D$47*('Operations & Capacity'!$B$11/'Operations & Capacity'!$B$19))+C25-C7-C8-C19)/(1-(Inputs!$B$116+Inputs!$B$121*Inputs!$B$117/365)) -> 31.732768 | F33: Price at which packing & selling nets the same per kg of bunch as the farm-gate price on Farm Plan (export column in US$/carton)
A35: Sensitivity – banana EXPORT net margin (₹/kg): CIF US$/carton (rows) × war-risk surcharge US$/reefer (columns)
A36: Export cost excl. surcharge & %-items | B36: =B25-B18-B19 -> 36.971573
A37: %-of-price items | B37: =Inputs!$B$103+Inputs!$B$104+Inputs!$B$105-N(Inputs!$B$106) -> 0.0405
A38: CIF US$/carton \ surcharge → | B38: 0 | C38: 1500 | D38: 3000 | E38: 4000 | F38: 4800
A39: 5 | B39: =$A39*Inputs!$B$6/Inputs!$B$62*(1-$B$37)-$B$36-B$38*Inputs!$B$6/(Inputs!$B$62*Inputs!$B$63) -> -1.5438805 | C39: =$A39*Inputs!$B$6/Inputs!$B$62*(1-$B$37)-$B$36-C$38*Inputs!$B$6/(Inputs!$B$62*Inputs!$B$63) -> -8.7366877 | D39: =$A39*Inputs!$B$6/Inputs!$B$62*(1-$B$37)-$B$36-D$38*Inputs!$B$6/(Inputs!$B$62*Inputs!$B$63) -> -15.929495 | E39: =$A39*Inputs!$B$6/Inputs!$B$62*(1-$B$37)-$B$36-E$38*Inputs!$B$6/(Inputs!$B$62*Inputs!$B$63) -> -20.7247 | F39: =$A39*Inputs!$B$6/Inputs!$B$62*(1-$B$37)-$B$36-F$38*Inputs!$B$6/(Inputs!$B$62*Inputs!$B$63) -> -24.560863
A40: 5.5 | B40: =$A40*Inputs!$B$6/Inputs!$B$62*(1-$B$37)-$B$36-B$38*Inputs!$B$6/(Inputs!$B$62*Inputs!$B$63) -> 1.9988888 | C40: =$A40*Inputs!$B$6/Inputs!$B$62*(1-$B$37)-$B$36-C$38*Inputs!$B$6/(Inputs!$B$62*Inputs!$B$63) -> -5.1939184 | D40: =$A40*Inputs!$B$6/Inputs!$B$62*(1-$B$37)-$B$36-D$38*Inputs!$B$6/(Inputs!$B$62*Inputs!$B$63) -> -12.386726 | E40: =$A40*Inputs!$B$6/Inputs!$B$62*(1-$B$37)-$B$36-E$38*Inputs!$B$6/(Inputs!$B$62*Inputs!$B$63) -> -17.18193 | F40: =$A40*Inputs!$B$6/Inputs!$B$62*(1-$B$37)-$B$36-F$38*Inputs!$B$6/(Inputs!$B$62*Inputs!$B$63) -> -21.018094
A41: 6 | B41: =$A41*Inputs!$B$6/Inputs!$B$62*(1-$B$37)-$B$36-B$38*Inputs!$B$6/(Inputs!$B$62*Inputs!$B$63) -> 5.541658 | C41: =$A41*Inputs!$B$6/Inputs!$B$62*(1-$B$37)-$B$36-C$38*Inputs!$B$6/(Inputs!$B$62*Inputs!$B$63) -> -1.6511492 | D41: =$A41*Inputs!$B$6/Inputs!$B$62*(1-$B$37)-$B$36-D$38*Inputs!$B$6/(Inputs!$B$62*Inputs!$B$63) -> -8.8439564 | E41: =$A41*Inputs!$B$6/Inputs!$B$62*(1-$B$37)-$B$36-E$38*Inputs!$B$6/(Inputs!$B$62*Inputs!$B$63) -> -13.639161 | F41: =$A41*Inputs!$B$6/Inputs!$B$62*(1-$B$37)-$B$36-F$38*Inputs!$B$6/(Inputs!$B$62*Inputs!$B$63) -> -17.475325
A42: 6.5 | B42: =$A42*Inputs!$B$6/Inputs!$B$62*(1-$B$37)-$B$36-B$38*Inputs!$B$6/(Inputs!$B$62*Inputs!$B$63) -> 9.0844272 | C42: =$A42*Inputs!$B$6/Inputs!$B$62*(1-$B$37)-$B$36-C$38*Inputs!$B$6/(Inputs!$B$62*Inputs!$B$63) -> 1.89162 | D42: =$A42*Inputs!$B$6/Inputs!$B$62*(1-$B$37)-$B$36-D$38*Inputs!$B$6/(Inputs!$B$62*Inputs!$B$63) -> -5.3011872 | E42: =$A42*Inputs!$B$6/Inputs!$B$62*(1-$B$37)-$B$36-E$38*Inputs!$B$6/(Inputs!$B$62*Inputs!$B$63) -> -10.096392 | F42: =$A42*Inputs!$B$6/Inputs!$B$62*(1-$B$37)-$B$36-F$38*Inputs!$B$6/(Inputs!$B$62*Inputs!$B$63) -> -13.932556
A43: 7 | B43: =$A43*Inputs!$B$6/Inputs!$B$62*(1-$B$37)-$B$36-B$38*Inputs!$B$6/(Inputs!$B$62*Inputs!$B$63) -> 12.627196 | C43: =$A43*Inputs!$B$6/Inputs!$B$62*(1-$B$37)-$B$36-C$38*Inputs!$B$6/(Inputs!$B$62*Inputs!$B$63) -> 5.4343893 | D43: =$A43*Inputs!$B$6/Inputs!$B$62*(1-$B$37)-$B$36-D$38*Inputs!$B$6/(Inputs!$B$62*Inputs!$B$63) -> -1.7584179 | E43: =$A43*Inputs!$B$6/Inputs!$B$62*(1-$B$37)-$B$36-E$38*Inputs!$B$6/(Inputs!$B$62*Inputs!$B$63) -> -6.5536227 | F43: =$A43*Inputs!$B$6/Inputs!$B$62*(1-$B$37)-$B$36-F$38*Inputs!$B$6/(Inputs!$B$62*Inputs!$B$63) -> -10.389787
A44: 7.5 | B44: =$A44*Inputs!$B$6/Inputs!$B$62*(1-$B$37)-$B$36-B$38*Inputs!$B$6/(Inputs!$B$62*Inputs!$B$63) -> 16.169966 | C44: =$A44*Inputs!$B$6/Inputs!$B$62*(1-$B$37)-$B$36-C$38*Inputs!$B$6/(Inputs!$B$62*Inputs!$B$63) -> 8.9771585 | D44: =$A44*Inputs!$B$6/Inputs!$B$62*(1-$B$37)-$B$36-D$38*Inputs!$B$6/(Inputs!$B$62*Inputs!$B$63) -> 1.7843513 | E44: =$A44*Inputs!$B$6/Inputs!$B$62*(1-$B$37)-$B$36-E$38*Inputs!$B$6/(Inputs!$B$62*Inputs!$B$63) -> -3.0108535 | F44: =$A44*Inputs!$B$6/Inputs!$B$62*(1-$B$37)-$B$36-F$38*Inputs!$B$6/(Inputs!$B$62*Inputs!$B$63) -> -6.8470173
A45: 8 | B45: =$A45*Inputs!$B$6/Inputs!$B$62*(1-$B$37)-$B$36-B$38*Inputs!$B$6/(Inputs!$B$62*Inputs!$B$63) -> 19.712735 | C45: =$A45*Inputs!$B$6/Inputs!$B$62*(1-$B$37)-$B$36-C$38*Inputs!$B$6/(Inputs!$B$62*Inputs!$B$63) -> 12.519928 | D45: =$A45*Inputs!$B$6/Inputs!$B$62*(1-$B$37)-$B$36-D$38*Inputs!$B$6/(Inputs!$B$62*Inputs!$B$63) -> 5.3271205 | E45: =$A45*Inputs!$B$6/Inputs!$B$62*(1-$B$37)-$B$36-E$38*Inputs!$B$6/(Inputs!$B$62*Inputs!$B$63) -> 0.53191573 | F45: =$A45*Inputs!$B$6/Inputs!$B$62*(1-$B$37)-$B$36-F$38*Inputs!$B$6/(Inputs!$B$62*Inputs!$B$63) -> -3.3042481
A46: 9 | B46: =$A46*Inputs!$B$6/Inputs!$B$62*(1-$B$37)-$B$36-B$38*Inputs!$B$6/(Inputs!$B$62*Inputs!$B$63) -> 26.798273 | C46: =$A46*Inputs!$B$6/Inputs!$B$62*(1-$B$37)-$B$36-C$38*Inputs!$B$6/(Inputs!$B$62*Inputs!$B$63) -> 19.605466 | D46: =$A46*Inputs!$B$6/Inputs!$B$62*(1-$B$37)-$B$36-D$38*Inputs!$B$6/(Inputs!$B$62*Inputs!$B$63) -> 12.412659 | E46: =$A46*Inputs!$B$6/Inputs!$B$62*(1-$B$37)-$B$36-E$38*Inputs!$B$6/(Inputs!$B$62*Inputs!$B$63) -> 7.6174542 | F46: =$A46*Inputs!$B$6/Inputs!$B$62*(1-$B$37)-$B$36-F$38*Inputs!$B$6/(Inputs!$B$62*Inputs!$B$63) -> 3.7812904
A48: Sensitivity – DOMESTIC net margin (₹/kg) by selling price
A49: Banana domestic: price ₹/kg → | B49: 22 | C49: 24 | D49: 26 | E49: 28 | F49: 30 | G49: 32 | H49: 34
A50: net margin ₹/kg | B50: =B49*(1-(Inputs!$B$116+Inputs!$B$121*Inputs!$B$117/365))-(C$25-C$19) -> -2.9026921 | C50: =C49*(1-(Inputs!$B$116+Inputs!$B$121*Inputs!$B$117/365))-(C$25-C$19) -> -0.9885825 | D50: =D49*(1-(Inputs!$B$116+Inputs!$B$121*Inputs!$B$117/365))-(C$25-C$19) -> 0.92552709 | E50: =E49*(1-(Inputs!$B$116+Inputs!$B$121*Inputs!$B$117/365))-(C$25-C$19) -> 2.8396367 | F50: =F49*(1-(Inputs!$B$116+Inputs!$B$121*Inputs!$B$117/365))-(C$25-C$19) -> 4.7537463 | G50: =G49*(1-(Inputs!$B$116+Inputs!$B$121*Inputs!$B$117/365))-(C$25-C$19) -> 6.6678559 | H50: =H49*(1-(Inputs!$B$116+Inputs!$B$121*Inputs!$B$117/365))-(C$25-C$19) -> 8.5819654
A51: Papaya: price ₹/kg → | B51: 18 | C51: 20 | D51: 22 | E51: 24 | F51: 26 | G51: 28 | H51: 30
A52: net margin ₹/kg | B52: =B51*(1-(Inputs!$B$116+Inputs!$B$121*Inputs!$B$117/365))-(D$25-D$19) -> -6.6889092 | C52: =C51*(1-(Inputs!$B$116+Inputs!$B$121*Inputs!$B$117/365))-(D$25-D$19) -> -4.7747996 | D52: =D51*(1-(Inputs!$B$116+Inputs!$B$121*Inputs!$B$117/365))-(D$25-D$19) -> -2.86069 | E52: =E51*(1-(Inputs!$B$116+Inputs!$B$121*Inputs!$B$117/365))-(D$25-D$19) -> -0.94658041 | F52: =F51*(1-(Inputs!$B$116+Inputs!$B$121*Inputs!$B$117/365))-(D$25-D$19) -> 0.96752918 | G52: =G51*(1-(Inputs!$B$116+Inputs!$B$121*Inputs!$B$117/365))-(D$25-D$19) -> 2.8816388 | H52: =H51*(1-(Inputs!$B$116+Inputs!$B$121*Inputs!$B$117/365))-(D$25-D$19) -> 4.7957484
A53: Kesar mango: price ₹/kg → | B53: 80 | C53: 90 | D53: 100 | E53: 110 | F53: 120 | G53: 130 | H53: 150
A54: net margin ₹/kg | B54: =B53*(1-(Inputs!$B$116+Inputs!$B$121*Inputs!$B$117/365))-(E$25-E$19) -> -24.498877 | C54: =C53*(1-(Inputs!$B$116+Inputs!$B$121*Inputs!$B$117/365))-(E$25-E$19) -> -14.928329 | D54: =D53*(1-(Inputs!$B$116+Inputs!$B$121*Inputs!$B$117/365))-(E$25-E$19) -> -5.3577809 | E54: =E53*(1-(Inputs!$B$116+Inputs!$B$121*Inputs!$B$117/365))-(E$25-E$19) -> 4.2127671 | F54: =F53*(1-(Inputs!$B$116+Inputs!$B$121*Inputs!$B$117/365))-(E$25-E$19) -> 13.783315 | G54: =G53*(1-(Inputs!$B$116+Inputs!$B$121*Inputs!$B$117/365))-(E$25-E$19) -> 23.353863 | H54: =H53*(1-(Inputs!$B$116+Inputs!$B$121*Inputs!$B$117/365))-(E$25-E$19) -> 42.494959

Sheet Waste Valorisation
A1: Waste streams – what can be sold, and the unit economics of each
A2: Banana culls → flour · pseudostem → fibre · sap → liquid fertiliser (blank) · stalks, papaya & mango culls → vermicompost.
A4: Item | B4: Value | C4: Unit | D4: Confidence | E4: Source / note
A5: A. Banana culls → green banana flour
A6: Banana culls available | B6: ='Operations & Capacity'!$B$17 -> 522.94737 | C6: t/yr | E6: Operations tab (only fruit that went through the packhouse)
A7: Share processed into flour | B7: 0.8 | C7: % | D7: Estimate
A8: Fresh : flour | B8: 5 | C8: kg per kg | D8: Researched | E8: [S27] 4:1–5:1
A9: Flour output | B9: =$B$6*$B$7*1000/$B$8 -> 83671.579 | C9: kg/yr
A10: Flour price (bulk B2B) | B10: 180 | C10: ₹/kg | D10: Derived | E10: [S27] ₹140–350/kg listings
A11: Drying energy | B11: 4 | C11: kWh/kg flour | D11: Estimate
A12: Labour | B12: 20 | C12: ₹/kg flour | D12: Estimate
A13: Packaging | B13: 8 | C13: ₹/kg flour | D13: Estimate
A14: Consumables & testing | B14: 5 | C14: ₹/kg flour | D14: Estimate
A15: Fixed: supervisor, FSSAI, marketing | B15: 600000 | C15: ₹/yr | D15: Estimate
A16: Capex: slicer, dryer, pulveriser, sealer | B16: 2500000 | C16: ₹ | D16: Estimate | E16: PMFME: 35% subsidy up to ₹10 L
A17: Life | B17: 10 | C17: years | D17: Estimate
A18: Alternative: sell culls as-is | B18: 8 | C18: ₹/kg | D18: Estimate | E18: [S20]
A19: Revenue | B19: =$B$9*$B$10 -> 15060884 | C19: ₹/yr
A20: Variable cost | B20: =$B$9*($B$11*Inputs!$B$48+$B$12+$B$13+$B$14) -> 5605995.8 | C20: ₹/yr
A21: EBITDA | B21: =$B$19-$B$20-$B$15 -> 8854888.4 | C21: ₹/yr
A22: Depreciation | B22: =$B$16/$B$17 -> 250000 | C22: ₹/yr
A23: Net profit | B23: =$B$21-$B$22 -> 8604888.4 | C23: ₹/yr
A24: Net margin per kg flour | B24: =IF($B$9=0,0,$B$23/$B$9) -> 102.84123 | C24: ₹/kg
A25: Gain vs selling culls as-is | B25: =$B$23-$B$6*$B$7*1000*$B$18 -> 5258025.3 | C25: ₹/yr
A26: B. Pseudostem → banana fibre
A27: Pseudostem biomass | B27: ='Operations & Capacity'!$B$25 -> 6821.0526 | C27: t/yr
A28: Share collected for fibre | B28: 0.3 | C28: % | D28: Estimate
A29: Fibre yield | B29: 0.01 | C29: % | D29: Researched | E29: [S28]
A30: Fibre output | B30: =$B$27*$B$28*$B$29*1000 -> 20463.158 | C30: kg/yr
A31: Raw fibre price | B31: 150 | C31: ₹/kg | D31: Researched | E31: [S29] ₹135–242/kg by grade
A32: Decorticator capacity | B32: 25 | C32: kg/machine/day | D32: Researched | E32: [S28]
A33: Working days | B33: 250 | C33: days/yr | D33: Estimate
A34: Machines | B34: =ROUNDUP($B$30/($B$32*$B$33),0) -> 4 | C34: machines
A35: Machine cost | B35: 500000 | C35: ₹/machine | D35: Researched | E35: [S28] US$3–8k
A36: Workers per machine | B36: 3 | C36: people | D36: Estimate
A37: Power | B37: 40 | C37: kWh/machine/day | D37: Estimate
A38: Collection & haulage | B38: 300 | C38: ₹/t pseudostem | D38: Estimate
A39: Consumables | B39: 5 | C39: ₹/kg fibre | D39: Estimate
A40: Revenue | B40: =$B$30*$B$31 -> 3069473.7 | C40: ₹/yr
A41: Operating cost | B41: =$B$34*$B$33*($B$36*Inputs!$B$45+$B$37*Inputs!$B$48)+$B$27*$B$28*$B$38+$B$30*$B$39 -> 2593710.5 | C41: ₹/yr
A42: EBITDA | B42: =$B$40-$B$41 -> 475763.16 | C42: ₹/yr
A43: Depreciation (5 yrs, + ₹2 L shed/machine) | B43: =$B$34*($B$35+200000)/5 -> 560000 | C43: ₹/yr | D43: Estimate
A44: Net profit | B44: =$B$42-$B$43 -> -84236.842 | C44: ₹/yr
A45: Net margin per kg fibre | B45: =IF($B$30=0,0,$B$44/$B$30) -> -4.1165123 | C45: ₹/kg
A46: Capex | B46: =$B$34*($B$35+200000) -> 2800000 | C46: ₹
A47: C. Pseudostem sap → liquid organic fertiliser
A48: Sap per tonne pseudostem | C48: litres/t | D48: Not found | E48: Left blank
A49: Bulk selling price | C49: ₹/litre | D49: Not found | E49: [S30] only retail ₹400–850/L found
A50: Processing & packing cost | C50: ₹/litre | D50: Not found | E50: Left blank
A51: Net profit (computes once filled) | B51: =IF(COUNT($B$48,$B$49,$B$50)<3,0,$B$27*$B$28*$B$48*($B$49-$B$50)) -> 0 | C51: ₹/yr
A52: D. Stalks, papaya & mango culls → vermicompost
A53: Feedstock: stalks + unused banana culls + papaya & mango culls + 10% pseudostem | B53: ='Operations & Capacity'!$B$15+$B$6*(1-$B$7)+'Operations & Capacity'!$C$17+'Operations & Capacity'!$D$17+$B$27*0.1 -> 1443.0316 | C53: t/yr | D53: Estimate
A54: Conversion | B54: 0.25 | C54: % | D54: Estimate
A55: Vermicompost output | B55: =$B$53*$B$54*1000 -> 360757.89 | C55: kg/yr
A56: Bulk price / value (own-farm use displaces FYM) | B56: 6 | C56: ₹/kg | D56: Researched | E56: [S31] ₹5–20/kg
A57: Labour + bagging | B57: 2 | C57: ₹/kg | D57: Estimate
A58: Capex | B58: 1000000 | C58: ₹ | D58: Estimate
A59: Revenue / value | B59: =$B$55*$B$56 -> 2164547.4 | C59: ₹/yr
A60: Operating cost | B60: =$B$55*$B$57 -> 721515.79 | C60: ₹/yr
A61: EBITDA | B61: =$B$59-$B$60 -> 1443031.6 | C61: ₹/yr
A62: Depreciation (5 yrs) | B62: =$B$58/5 -> 200000 | C62: ₹/yr
A63: Net margin per kg | B63: =IF($B$55=0,0,($B$61-$B$62)/$B$55) -> 3.4456116 | C63: ₹/kg
A64: E. Not modelled
A65: Mango culls → pulp units | E65: Pulp makers buy culls in season; no reliable price found – sent to compost instead.
A66: Banana leaves | E66: Limited demand in Gujarat.
A67: Carbon credits | E67: Too small to verify.
A69: Summary
A70: By-product revenue | B70: =$B$19+$B$40+$B$59+IF(COUNT($B$48,$B$49,$B$50)<3,0,$B$27*$B$28*$B$48*$B$49) -> 20294905 | C70: ₹/yr
A71: By-product operating cost | B71: =$B$20+$B$15+$B$41+$B$60+IF(COUNT($B$48,$B$49,$B$50)<3,0,$B$27*$B$28*$B$48*$B$50) -> 9521222.1 | C71: ₹/yr
A72: By-product EBITDA | B72: =$B$70-$B$71 -> 10773683 | C72: ₹/yr
A73: Depreciation | B73: =$B$22+$B$43+$B$62 -> 1010000 | C73: ₹/yr
A74: Capex | B74: =$B$16+$B$46+$B$58 -> 6300000 | C74: ₹

Sheet Annual P&L
A1: Consolidated annual P&L – Sitpur farm + multi-fruit packhouse + pre-cooling + cold storage + by-products
A2: Column B follows Inputs (war-risk surcharge ON = Sep-2026). Column D = normalised year with no surcharge.
A4: Line item (₹/yr) | B4: As set on Inputs | C4: ₹ per kg sellable | D4: Normalised (no surcharge) | E4: Note
A5: Revenue
A6: Banana export | B6: ='Unit Economics'!$B$5*('Operations & Capacity'!$B$20*1000) -> 59910460 | C6: =B6/('Operations & Capacity'!$E$19*1000) -> 9.6468695 | D6: =B6 -> 59910460
A7: Banana domestic premium | B7: ='Unit Economics'!$C$5*('Operations & Capacity'!$B$21*1000) -> 97354497 | C7: =B7/('Operations & Capacity'!$E$19*1000) -> 15.676163 | D7: =B7 -> 97354497
A8: Banana surplus sold at farm gate (not processed) | B8: ='Operations & Capacity'!$B$12*1000*'Farm Plan'!$D$47 -> 0 | C8: =B8/('Operations & Capacity'!$E$19*1000) -> 0 | D8: =B8 -> 0 | E8: Only if running days/capacity are too low
A9: Papaya | B9: ='Unit Economics'!$D$5*('Operations & Capacity'!$C$19*1000) -> 32452992 | C9: =B9/('Operations & Capacity'!$E$19*1000) -> 5.2256281 | D9: =B9 -> 32452992
A10: Kesar mango | B10: ='Unit Economics'!$E$5*('Operations & Capacity'!$D$19*1000) -> 39147840 | C10: =B10/('Operations & Capacity'!$E$19*1000) -> 6.3036423 | D10: =B10 -> 39147840
A11: Rotation crop (scenario) | B11: ='Crop Rotation'!$B$27 -> 0 | C11: =B11/('Operations & Capacity'!$E$19*1000) -> 0 | D11: =B11 -> 0
A12: By-products | B12: ='Waste Valorisation'!$B$70 -> 20294905 | C12: =B12/('Operations & Capacity'!$E$19*1000) -> 3.2679152 | D12: =B12 -> 20294905
A13: TOTAL REVENUE | B13: =SUM(B6:B12) -> 2.4916069e+08 | C13: =B13/('Operations & Capacity'!$E$19*1000) -> 40.120218 | D13: =SUM(D6:D12) -> 2.4916069e+08
A14: Operating costs
A15: Farm: inputs + fixed costs (owner plan) | B15: ='Farm Plan'!$D$43 -> 39413737 | C15: =B15/('Operations & Capacity'!$E$19*1000) -> 6.3464574 | D15: =B15 -> 39413737
A16: Papaya & mango procurement incl. inbound freight | B16: ='Operations & Capacity'!$C$11*1000*(Inputs!$B$77+Inputs!$B$78)+'Operations & Capacity'!$D$11*1000*(Inputs!$B$87+Inputs!$B$88) -> 45000000 | C16: =B16/('Operations & Capacity'!$E$19*1000) -> 7.2459656 | D16: =B16 -> 45000000
A17: Harvest crew (≤ ₹1,000/day) | B17: ='Packhouse Opex'!$B$36 -> 5684210.5 | C17: =B17/('Operations & Capacity'!$E$19*1000) -> 0.91527987 | D17: =B17 -> 5684210.5
A18: Packhouse lines opex (labour, loading, chemicals, power, staff, R&M) | B18: ='Packhouse Opex'!$B$37 -> 14210963 | C18: =B18/('Operations & Capacity'!$E$19*1000) -> 2.28827 | D18: =B18 -> 14210963
A19: PRE-COOLING opex | B19: ='Packhouse Opex'!$B$38 -> 1806657.5 | C19: =B19/('Operations & Capacity'!$E$19*1000) -> 0.29091062 | D19: =B19 -> 1806657.5
A20: COLD STORAGE opex | B20: ='Packhouse Opex'!$B$39 -> 1526140 | C20: =B20/('Operations & Capacity'!$E$19*1000) -> 0.24574129 | D20: =B20 -> 1526140
A21: Common overheads | B21: ='Packhouse Opex'!$B$40 -> 3429571.2 | C21: =B21/('Operations & Capacity'!$E$19*1000) -> 0.55223456 | D21: =B21 -> 3429571.2
A22: Packaging – all fruits | B22: ='Unit Economics'!$B$13*('Operations & Capacity'!$B$20*1000)+'Unit Economics'!$C$13*('Operations & Capacity'!$B$21*1000)+'Unit Economics'!$D$13*('Operations & Capacity'!$C$19*1000)+'Unit Economics'!$E$13*('Operations & Capacity'!$D$19*1000) -> 32959012 | C22: =B22/('Operations & Capacity'!$E$19*1000) -> 5.3071082 | D22: =B22 -> 32959012
A23: Banana export logistics excl. surcharge | B23: =('Unit Economics'!$B$14+'Unit Economics'!$B$15+'Unit Economics'!$B$16+'Unit Economics'!$B$17)*('Operations & Capacity'!$B$20*1000) -> 17830494 | C23: =B23/('Operations & Capacity'!$E$19*1000) -> 2.8710921 | D23: =B23 -> 17830494
A24: Gulf war-risk surcharge | B24: ='Unit Economics'!$B$18*('Operations & Capacity'!$B$20*1000) -> 22230226 | C24: =B24/('Operations & Capacity'!$E$19*1000) -> 3.5795434 | D24: =0 -> 0 | E24: Only difference between B and D
A25: Domestic reefer freight – all fruits | B25: ='Unit Economics'!$C$15*(('Operations & Capacity'!$B$21*1000)+('Operations & Capacity'!$C$19*1000)+('Operations & Capacity'!$D$19*1000)) -> 24022072 | C25: =B25/('Operations & Capacity'!$E$19*1000) -> 3.8680691 | D25: =B25 -> 24022072
A26: Insurance, bank, claims, trade schemes, receivables | B26: ='Unit Economics'!$B$19*('Operations & Capacity'!$B$20*1000)+'Unit Economics'!$C$19*('Operations & Capacity'!$B$21*1000)+'Unit Economics'!$D$19*('Operations & Capacity'!$C$19*1000)+'Unit Economics'!$E$19*('Operations & Capacity'!$D$19*1000) -> 9682194.9 | C26: =B26/('Operations & Capacity'!$E$19*1000) -> 1.5590411 | D26: =B26 -> 9682194.9
A27: Rotation crop costs (scenario) | B27: ='Crop Rotation'!$B$28 -> 0 | C27: =B27/('Operations & Capacity'!$E$19*1000) -> 0 | D27: =B27 -> 0
A28: By-product processing | B28: ='Waste Valorisation'!$B$71 -> 9521222.1 | C28: =B28/('Operations & Capacity'!$E$19*1000) -> 1.5331211 | D28: =B28 -> 9521222.1
A29: TOTAL OPERATING COST | B29: =SUM(B15:B28) -> 2.273165e+08 | C29: =B29/('Operations & Capacity'!$E$19*1000) -> 36.602834 | D29: =SUM(D15:D28) -> 2.0508627e+08
A30: EBITDA | B30: =B13-B29 -> 21844193 | C30: =B30/('Operations & Capacity'!$E$19*1000) -> 3.5173838 | D30: =D13-D29 -> 44074419
A31: EBITDA margin | B31: =IF(B13=0,0,B30/B13) -> 0.087671102 | D31: =IF(D13=0,0,D30/D13) -> 0.17689154
A32: Depreciation – farm + packhouse/pre-cooling/cold storage + by-products | B32: ='Farm Plan'!$D$36+'Packhouse Capex'!$J$25+'Waste Valorisation'!$B$73 -> 5693250 | C32: =B32/('Operations & Capacity'!$E$19*1000) -> 0.91673541 | D32: =B32 -> 5693250
A33: Interest – packhouse loan (average) | B33: ='Packhouse Capex'!$B$35 -> 804608.52 | C33: =B33/('Operations & Capacity'!$E$19*1000) -> 0.12955924 | D33: =B33 -> 804608.52 | E33: Farm plan has no borrowing modelled
A34: PROFIT BEFORE TAX | B34: =B30-B32-B33 -> 15346334 | C34: =B34/('Operations & Capacity'!$E$19*1000) -> 2.4710891 | D34: =D30-D32-D33 -> 37576560
A35: Tax not computed: farm income may be exempt u/s 10(1); packhouse, trading and by-product income is taxable (DPR assumed 25%). Consult a CA.
A37: Cash & returns (packhouse project)
A38: Packhouse + pre-cooling + cold storage + by-product capex | B38: ='Packhouse Capex'!$E$25+'Waste Valorisation'!$B$74 -> 35857500 | C38: =B38/('Operations & Capacity'!$E$19*1000) -> 5.7738269 | D38: =B38 -> 35857500
A39: Less: MIDH subsidy | B39: =-'Packhouse Capex'!$H$25 -> -4655000 | C39: =B39/('Operations & Capacity'!$E$19*1000) -> -0.74955489 | D39: =B39 -> -4655000
A40: Net capex | B40: =B38+B39 -> 31202500 | C40: =B40/('Operations & Capacity'!$E$19*1000) -> 5.024272 | D40: =D38+D39 -> 31202500
A41: Packhouse business EBITDA after paying the farm the farm-gate price for its bananas | B41: =B30-('Farm Plan'!$D$46-'Farm Plan'!$D$43-'Packhouse Opex'!$B$36) -> -9794702 | C41: =B41/('Operations & Capacity'!$E$19*1000) -> -1.5771572 | D41: =D30-('Farm Plan'!$D$46-'Farm Plan'!$D$43-'Packhouse Opex'!$B$36) -> 12435524 | E41: Value the packhouse adds over selling at farm gate
A42: Payback of net packhouse capex on value added (years) | B42: =IF(B41<=0,"n/a",B40/B41) -> n/a | D42: =IF(D41<=0,"n/a",D40/D41) -> 2.5091423
A43: Annual EMI | B43: ='Packhouse Capex'!$B$34 -> 3306483.5 | C43: =B43/('Operations & Capacity'!$E$19*1000) -> 0.5324148 | D43: =B43 -> 3306483.5

Sheet Plan vs Model
A1: Your farm plan & Sitpur DPR vs this workbook
A2: What was taken from your documents, and where this model differs.
A4: Topic | B4: Farm plan / DPR | C4: This model | D4: Comment
A5: Plants / yield / cycle | B5: 1,200 plants/acre; 25 kg/plant plant & ratoon; 11 + 8 months | C5: Same (Inputs) | D5: Ratoon 25 kg is optimistic per your plan's own note – test 20 kg.
A6: Annual banana output | B6: 5,684 t (annualised) | C6: ='Farm Plan'!$D$40 -> 5684.2105 | D6: Matches when shortfall and rotation acres are 0.
A7: Inputs per plant | B7: ₹125 plant / ₹50 ratoon | C7: Same
A8: Farm fixed costs | B8: ₹195.19 L/yr | C8: ='Farm Plan'!$D$28/100000 -> 195.19 | D8: Same line items; toggle for workers already inside per-plant inputs.
A9: Harvest handling | B9: ₹10/plant (₹0.40/kg) | C9: Crew model ≤ ₹1,000/day (~₹1/kg) | D9: Uses your 13-person/13 t note and the ₹1,000/day cap.
A10: Farm capex | B10: ₹138 L; depreciation ₹19.13 L/yr | C10: ='Farm Plan'!$B$36/100000 -> 138
A11: Packhouse design | B11: 25 MT/day × ~300 days | C11: Same, plus 8 t/day multi-fruit line | D11: Running days drive capacity and costs.
A12: Ripening chamber | B12: 20–25 MT, ₹45 L | C12: Not included | D12: You asked to sell pre-ripened (green) fruit. Add it back if you move to ripened supply for quick-commerce.
A13: Cold storage | B13: 20–25 MT | C13: =Inputs!$B$16 -> 100 | D13: Two chambers (banana / papaya+mango); room to stage export containers.
A14: Capex | B14: ₹172 L fixed | C14: ='Packhouse Capex'!$E$25/100000 -> 295.575 | D14: Market listings for integrated packhouse + 3 pre-coolers; see Capex tab comparison.
A15: Sourcing | B15: Buy from growers at ₹14/kg + Sitpur anchor | C15: Own banana + procured papaya & mango | D15: Buying outside banana can be added if the line has spare capacity.
A16: Prices | B16: Domestic ₹26/kg, export ₹30/kg (planning) | C16: Banana ₹28 domestic; CIF ₹51.7/kg export | D16: Your DPR says to validate against eNAM/APMC.
A17: Loan | B17: 7 yrs @ 9.5% | C17: 7 yrs @ 10.5% − 3% AIF
A18: Export gateway | B18: Hazira/Surat ~170 km | C18: =Inputs!$B$96 -> 60000 | D18: Inland cost kept at your ₹60k (JNPT/Mundra); lower it if Hazira reefer services work.
A19: Farm wages | B19: 50 workers × ₹400/day | C19: Unchanged | D19: Below Gujarat minimum wage (₹501–512/day) – flagged.

Sheet Location & Risks
A1: Sitpur (Dabhoi, Vadodara) – location factors & key risks
A2: Qualitative – supports the numbers.
A4: Factor | B4: Assessment | C4: Implication | D4: Source
A5: Site | B5: 3–5 acre carve-out of Sitpur Estate (22.063° N, 73.479° E), Narmada-facing belt of Dabhoi taluka; banana on the estate since 2010. | C5: Zero-transport anchor supply; site lease from the family (terms open). | D5: DPR
A6: Connectivity | B6: Dabhoi Junction ~14 km; Vadodara ~55 km; Hazira/Surat ~170 km; Nhava Sheva ~430 km. | C6: Hazira could cut export haulage if reefer services suit. | D6: DPR
A7: Fruit catchment | B7: Papaya: Anand & Vadodara top papaya districts. Mango: Valsad/Navsari ~150–200 km, Gir ~400 km. Banana: Vadodara/Anand/Bharuch/Narmada. | C7: Papaya within same-day collection; mango needs longer inbound runs. | D7: [S34][S37][S4]
A8: Monoculture risk | B8: Banana on the same land since 2010 raises Fusarium wilt and nematode pressure. | C8: Rotation crop + green manure tab; clean TC plants. | D8: [S43]
A9: Gulf shipping (2026) | B9: Hormuz effectively closed; US$3,500–4,800/reefer surcharges; transits 20–30+ days. | C9: Banana export margin negative until surcharges ease. | D9: [S18][S19][S16]
A10: Ethylene & temperature | B10: Banana, papaya, mango all ~13 °C, but papaya/mango emit ethylene. | C10: Two cold chambers; shared pre-cooling is fine with short dwell. | D10: [S44]
A11: Labour | B11: Minimum wage ₹501.50–512.50/day; harvest/loading capped at ₹1,000/day by your rule. | C11: Plan's ₹400/day farm wage is below minimum. | D11: [S6]
A12: Subsidy | B12: MIDH 35%; APEDA FAS up to 40% for registered exporters; AIF 3% interest subvention. | C12: Included (MIDH + AIF). | D12: [S22][S23]

Sheet Sources
A1: Sources (accessed Sep-2026)
A2: Referenced as [S#]. Your documents: Banana Farm Business Plan (150 acres, Sep-2026) and Sitpur DPR (16-Sep-2026).
A4: # | B4: Source | C4: URL
A5: S1 | B5: USD/INR 95.96 on 25-Sep-2026 (Trading Economics / Fed H.10) | C5: https://tradingeconomics.com/india/currency
A6: S2 | B6: Grand Nain (G9) cultivation guide – spacing, 11–12 month maturity in Gujarat | C6: https://www.agrifarming.in/grand-nain-g9-banana-farming-in-india-a-cultivation-guide-to-planting-to-harvesting
A7: S3 | B7: Agro Potli – Banana farming in India 2026: cost ₹84k–1.25 lakh/acre, TC ₹10–15/plant, yields 20–40 / 10–20 t/acre | C7: https://agropotli.com/banana-farming-in-india-complete-guide-2026/
A8: S4 | B8: DeshGujarat – Gujarat banana productivity 65.91 t/ha; Bharuch 72.55 t/ha; cluster districts | C8: https://deshgujarat.com/2024/11/11/gujarat-ranks-3rd-in-banana-production-nationwide-tops-in-productivity-per-hectare-globally/
A9: S5 | B9: Swasya – Cost to lease farmland in India 2025 (₹30,000–80,000/acre/yr irrigated) | C9: https://www.swasya.com/blog/cost-to-lease-farmland-in-india
A10: S6 | B10: Gujarat minimum wages 1-Apr-2026 to 30-Sep-2026 (₹512.50/₹501.50 per day unskilled) | C10: https://www.sgcms.com/regulatory-updates/minimum-rate-of-wages-gujarat-april-2026/
A11: S7 | B11: Comparative economics of banana cultivation in Anand district (160.6 man-days/ha on drip farms; plantlets ~22.7% of cost) | C11: https://www.researchgate.net/publication/304528951_Comparative_economics_of_Banana_cultivation_in_Anand_district_of_Gujarat
A12: S8 | B12: Netafim India – Cost and ROI of banana drip irrigation per acre (~₹25,000) | C12: https://www.netafimindia.com/blog/cost-and-roi-of-banana-drip-irrigation-per-acre/
A13: S9 | B13: IndiaMART – Banana 13 kg export corrugated box ₹84/piece (Nashik) | C13: https://www.indiamart.com/proddetail/banana-13-kg-export-corrugated-packing-box-23108020130.html
A14: S10 | B14: Exim Internationals – Cavendish banana export packaging specs 2026 | C14: https://eximinternationals.com/cavendish-banana-export-packaging-specifications/
A15: S11 | B15: Exim Internationals – Import bananas from India to UAE (40' HC ≈1,540 boxes, 13–14 °C) | C15: https://eximinternationals.com/import-bananas-from-india-to-uae
... A50: S46 | B50: IndiaMART – pomegranate Kutch ₹30/kg A-grade (Jun-2026); Gujarat wholesale ₹115/kg | C50: https://dir.indiamart.com/kutch/fresh-pomegranates.html

Sheet Original Draft
A1: Cost Component | B1: Cost per KG (INR) | C1: Cost per Container (INR) | D1: Notes / Details | I1: Your original draft – kept unchanged for reference. The model tabs replace these figures.
A2: Raw Banana Procurement | B2: ₹15.00 | C2: ₹3,00,300 | D2: Average annualized price (Fluctuates between ₹11 in peak season to ₹21 in lean season).
A3: Rejection Allowance (5%) | B3: ₹0.75 | C3: ₹15,015 | D3: Covers field-bruised, undersized, or over-mature fruits sorted out at your packhouse.
A4: Export-Grade Packaging | B4: ₹6.50 | C4: ₹1,30,130 | D4: Includes 5-ply Top/Bottom Telescopic CFB Box, 100-gauge Polybag/Foam pad, and branded stickers. | E4: Understated | F4: A real 13kg telescopic export carton (the exact box type named) sells for ~₹84/piece — that alone is ₹6.46/kg, leaving almost nothing in the ₹6.50 budget for the poly liner/Banavac bag, foam pad, and stickers the line item says it covers | G4: ₹8–10/kg
A5: Packhouse Consumables | B5: ₹0.40 | C5: ₹8,008 | D5: Alum wash, food-grade post-harvest fungicide treatment, and fresh water.
A6: Boxes
A7: Plastic liners/foam sheet
A8: chemical treatment
A9: power
A10: administrative overheads
A12: Direct Labour | B12: ₹1.50 | C12: ₹30,030 | D12: De-handing, washing, grading, weighing, and packing staff.
A14: Power & Utilities | B14: ₹0.50 | C14: ₹10,010 | D14: Running water pumps, conveyers, and blast pre-cooling units.
A15: Inland Logistics (Port) | B15: ₹3.00 | C15: ₹60,060 | D15: Transport from packhouse to JNPT (Mumbai) / Mundra port via a temperature-controlled reefer truck.
A16: Customs, CHA & APEDA | B16: ₹1.00 | C16: ₹20,020 | D16: Custom House Agent charges, Phytosanitary certificate, and documentation.
A17: Ocean Freight (India to UAE) | B17: ₹4.50 | C17: ₹90,090 | D17: Average sea freight cost for a refrigerated container (~$1,000 – $1,200 USD). | E17: Understated | F17: Reefer-specific rates (not standard dry container) run $1,500–3,000 once you add the power/genset surcharge reefers carry | G17: ₹7–8/kg
A18: TOTAL landed cost (CIF Dubai) | B18: ₹33.15 | C18: ₹6,63,663 | D18: Your total break-even cost landed at Jebel Ali Port.
A20: Fixed Costs
A21: Employees
A22: Interest on loan
A23: Cold storage cost
A25: Farming Input Cost | B25: 14
A26: fertiliser
A27: seeds
A28: crop protection
A29: water
A30: labour
A31: rent
A33: Post harvest management cost
A34: 13 tonnes requires 10 people 1000 rs per day | B34: 1
A35: 3 harvesters 1000rs per day
A37: Pack house fixed cost
A38: water
A39: electricity
A40: cold storage
A41: admin
A42: labour manager
A43: rental
A46: How many days is the banana harvest there
A49: Packhouse and cold storage ka variable and fixed cost
A50: banana packhouse location macro factors
A51: 2 crop seasonality choice
... A55: price fluctuation
